Sequential Design/Assignment-2/Code/Question1/d_ff.v


    module d_ff(input clk, rst, d, output reg q);
    
    always @(posedge clk or posedge rst) begin
        if (rst)
            q <= 0;
        else
            q <= d; 
    end
    endmodule

Sequential Design/Assignment-2/Code/Question1/d_ff2.v


    module d_ff2 (input clk, rst, d, output reg q);
    
    always @(posedge clk or posedge rst) begin
        if (rst)
        //LSB = 1 for 1-Hot Encoding
            q <= 1;
        else
            q <= d; 
    end
    endmodule

Sequential Design/Assignment-2/Code/Question1/button_press_synchronizer.v


        module button_press_synchronizer (input clk, rst, bi, output reg bo);
        
        wire Da, Db, Dc, Qa, Qb, Qc;

        d_ff2 A(.d(Da), .clk(clk), .rst(rst), .q(Qa));
        d_ff B(.d(Db), .clk(clk), .rst(rst), .q(Qb));
        d_ff C(.d(Dc), .clk(clk), .rst(rst), .q(Qc));


        assign Da = ~bi;
        assign Db = bi & Qa;
        assign Dc = ~Qa & bi;
        assign bo = Qb;

        /*localparam S0 = 3'b001;
        localparam S1 = 3'b010;
        localparam S2 = 3'b100;

        reg [2:0] state, next_state;

        //Transition Logic
        always @(posedge clk or posedge rst) begin
            if (rst)
                state <= S0;
            else
                state <= next_state;
        end

        //Next State Logic
        always @(*) begin
            case (state)
            
            S0: next_state = (bi) ? S1 : S0;

            S1: next_state = (bi) ? S2 : S0;

            S2: next_state = (bi) ? S2 : S0;
            endcase
        end
        
        //Output Logic
        always @(*) begin
            case (state)
            
            S0: bo = 0;

            S1: bo = 1;

            S2: bo = 0;
            endcase
        end*/
    
        endmodule

Sequential Design/Assignment-2/Code/Question1/tb_button_press_synchronizer.v

    module tb_button_press_synchronizer;
    reg clk, rst, bi;
    wire bo;

    button_press_synchronizer m1 (.clk(clk), .rst(rst), .bi(bi), .bo(bo));

    initial begin
        clk = 0;
        rst = 0;
        bi = 0;
    end

    always #5 clk = ~clk;
    initial begin
        
        $dumpvars;

        repeat(2) @(posedge clk);
        
        rst = 1;
        repeat(3) @(posedge clk);

        rst = 0;
        @(posedge clk);
        bi = 1;

        repeat (1.5) @(posedge clk)
        $display("Checking for Output Pulse");
        if (bo != 1) begin
            $display("Output is Incorrect Error: Line: 31");
            $finish;
            end
        
        repeat (1.5) @(posedge clk);
        $display("Checking if Output had one cycle");
        if (bo != 0) begin
            $display("Output is Incorrect Error: Line: 38");
            $finish;
            end

        bi = 0;

        repeat(5) @(posedge clk);

        //Asserting Input again
        bi = 1;
        repeat(5) @(posedge clk);
        bi = 0;

        if (bo != 0) begin
            @(posedge clk)
            if (bo != 1) begin
            $display("Output is Incorrect Line: 49");
            $finish;
            end
        end
    
        repeat(15) @(posedge clk);


        $display("All Test cases Passed!");
        $finish;
    end

    endmodule

Sequential Design/Assignment-2/Code/Question1/dump.vcd
$date
	Sat Jul 27 13:59:00 2024
$end
$version
	ModelSim Version 2020.1
$end
$timescale
	1ps
$end

$scope module tb_button_press_synchronizer $end
$var reg 1 ! clk $end
$var reg 1 " rst $end
$var reg 1 # bi $end
$var wire 1 $ bo $end

$scope module m1 $end
$var wire 1 % clk $end
$var wire 1 & rst $end
$var wire 1 ' bi $end
$var reg 1 ( bo $end
$var wire 1 ) Da $end
$var wire 1 * Db $end
$var wire 1 + Dc $end
$var wire 1 , Qa $end
$var wire 1 - Qb $end
$var wire 1 . Qc $end

$scope module A $end
$var wire 1 % clk $end
$var wire 1 & rst $end
$var wire 1 ) d $end
$var reg 1 / q $end
$upscope $end

$scope module B $end
$var wire 1 % clk $end
$var wire 1 & rst $end
$var wire 1 * d $end
$var reg 1 0 q $end
$upscope $end

$scope module C $end
$var wire 1 % clk $end
$var wire 1 & rst $end
$var wire 1 + d $end
$var reg 1 1 q $end
$upscope $end
$upscope $end
$upscope $end
$enddefinitions $end
#0
$dumpvars
0!
0"
0#
x(
x/
x0
x1
x$
1)
0*
0+
x,
x-
x.
0'
0&
0%
$end
#5
1!
1%
1/
00
01
1,
0-
0.
0(
0$
#10
0!
0%
#15
1!
1%
1"
1&
#20
0!
0%
#25
1!
1%
#30
0!
0%
#35
1!
1%
#40
0!
0%
#45
1!
1%
0"
0&
#50
0!
0%
#55
1!
1%
1#
1'
0)
1*
#60
0!
0%
#65
1!
1%
0/
10
0,
1-
0*
1+
1(
1$
#70
0!
0%
#75
1!
1%
00
11
0-
1.
0(
0$
#80
0!
0%
#85
1!
1%
#90
0!
0%
#95
1!
1%
0#
0'
1)
0+
#100
0!
0%
#105
1!
1%
1/
01
1,
0.
#110
0!
0%
#115
1!
1%
#120
0!
0%
#125
1!
1%
#130
0!
0%
#135
1!
1%
#140
0!
0%
#145
1!
1%
1#
1'
0)
1*
#150
0!
0%
#155
1!
1%
0/
10
0,
1-
0*
1+
1(
1$
#160
0!
0%
#165
1!
1%
00
11
0-
1.
0(
0$
#170
0!
0%
#175
1!
1%
#180
0!
0%
#185
1!
1%
#190
0!
0%
#195
1!
1%
0#
0'
1)
0+
#200
0!
0%
#205
1!
1%
1/
01
1,
0.
