Sequential Design/Assignment-2/Code/Question1/button_press_synchronizer.v


        module button_press_synchronizer (input clk, rst, bi, output reg bo);
        

        localparam S0 = 3'b001;
        localparam S1 = 3'b010;
        localparam S2 = 3'b100;

        reg [2:0] state;
        


        always @(posedge clk or posedge rst)
        begin
            if (rst)
                state <= S0;
            else
             begin 
                case (state)
                S0 : state <= bi? S1 : S0;

                S1 : state <= S2;

                S2 : state <= bi ? S2 : S0;
            endcase
            end
        end

        always @(state)
            case (state)
            S0 : bo <= 0;

            S1 : bo <= 1;

            S2 : bo <= 0;

            default : bo <= bo;
            endcase
        endmodule

Sequential Design/Assignment-2/Code/Question1/tb_button_press_synchronizer.v

    module tb_button_press_synchronizer;
    reg clk, rst, bi;
    wire bo;

    button_press_synchronizer m1 (.clk(clk), .rst(rst), .bi(bi), .bo(bo));

    always #5 clk = ~clk;
    initial begin
        
        $dumpvars;

        clk = 0;
        rst = 0;
        bi = 0;

        #10;
        rst = 1;
        bi = 1;

        #20
        rst = 0;

        #30;
        bi = 0;

        #20;
        bi = 1;

        #50;
        bi = 0;

        #10;
        bi = 1;

        #20;
        bi = 0;

        $finish;
    end


    endmodule

Sequential Design/Assignment-2/Code/Question1/dump.vcd
$date
	Thu Jul 18 12:14:06 2024
$end
$version
	ModelSim Version 2020.1
$end
$timescale
	1ps
$end

$scope module tb_button_press_synchronizer $end
$var reg 1 ! clk $end
$var reg 1 " rst $end
$var reg 1 # bi $end
$var wire 1 $ bo $end

$scope module m1 $end
$var parameter 3 % S0 $end
$var parameter 3 & S1 $end
$var parameter 3 ' S2 $end
$var wire 1 ( clk $end
$var wire 1 ) rst $end
$var wire 1 * bi $end
$var reg 1 + bo $end
$var reg 3 , state [2:0] $end
$upscope $end
$upscope $end
$enddefinitions $end
#0
$dumpvars
0!
0"
0#
x+
bx ,
b1 %
b10 &
b100 '
x$
0*
0)
0(
$end
#5
1!
1(
#10
1"
1#
0!
1*
1)
0(
b1 ,
0+
0$
#15
1!
1(
#20
0!
0(
#25
1!
1(
#30
0"
0!
0)
0(
#35
1!
1(
b10 ,
1+
1$
#40
0!
0(
#45
1!
1(
b100 ,
0+
0$
#50
0!
0(
#55
1!
1(
#60
0#
0!
0*
0(
#65
1!
1(
b1 ,
#70
0!
0(
#75
1!
1(
#80
1#
0!
1*
0(
#85
1!
1(
b10 ,
1+
1$
#90
0!
0(
#95
1!
1(
b100 ,
0+
0$
#100
0!
0(
#105
1!
1(
#110
0!
0(
#115
1!
1(
#120
0!
0(
#125
1!
1(
#130
0#
0!
0*
0(
#135
1!
1(
b1 ,
#140
1#
0!
1*
0(
#145
1!
1(
b10 ,
1+
1$
#150
0!
0(
#155
1!
1(
b100 ,
0+
0$
#160
0#
