Sequential Design/Assignment-2/Code/Question4/pulse_detector.v


    module pulse_detector (input clk, rst, x, output reg y);
    
    localparam A = 3'b001;
    localparam B = 3'b010;
    localparam C = 3'b100;

    reg [2:0] state, next_state;
    reg x_previous;

    //State-Transition
    always @(posedge clk or rst)
    begin
    if (rst) 
        state <= A;
    else
    state <= next_state;
    end

    //Next-State Logic
    always @(*)
    begin 
    case (state)

    A : 
    begin 
        if (!x)
        next_state <= A;
        else
        next_state <= B;
    end
    
    B : 
    begin 
        if (!x && x_previous)
        next_state <= C;
        else
        next_state <= B;
    end

    C : next_state <= A;
    default : next_state <= A;
    endcase
    end

    //Output
    always @(posedge clk or posedge rst)
    begin
        if (rst)
            y <= 0;
        else if (state == C)
            y <= 1;
        else
            y <= 0;
    end

    //Detect Failling-Edge
    always @(posedge clk or posedge rst)
    begin
        if (rst)
            x_previous <= 1;
        else
            x_previous <= x;
    end

    endmodule

Sequential Design/Assignment-2/Code/Question4/tb_pulse_detector.v
module tb_pulse_detector;

reg clk, rst, x;
wire y;

pulse_detector m0 (.clk(clk), .rst(rst), .x(x), .y(y));

always #5 clk = ~clk;

initial begin
    $dumpvars;
    
    clk = 0;
    rst = 0;
    x = 1;
    #20;
    
    rst = 1;
    #20;

    rst = 0;
    #10;

    x = 0;
    #20;

    x = 1;
    #20;

    x = 0;
    #30;

    x = 1;
    #40;
    
    rst = 1;
    #10;
    
    x = 0;    
    #30;
    
    x = 1;
    rst = 0;
    #40;

    $finish;
end
endmodule

Sequential Design/Assignment-2/Code/Question4/dump.vcd
$date
	Fri Jul 19 12:07:44 2024
$end
$version
	ModelSim Version 2020.1
$end
$timescale
	1ps
$end

$scope module tb_pulse_detector $end
$var reg 1 ! clk $end
$var reg 1 " rst $end
$var reg 1 # x $end
$var wire 1 $ y $end

$scope module m0 $end
$var parameter 3 % A $end
$var parameter 3 & B $end
$var parameter 3 ' C $end
$var wire 1 ( clk $end
$var wire 1 ) rst $end
$var wire 1 * x $end
$var reg 1 + y $end
$var reg 3 , state [2:0] $end
$var reg 3 - next_state [2:0] $end
$var reg 1 . x_previous $end
$upscope $end
$upscope $end
$enddefinitions $end
#0
$dumpvars
0!
0"
1#
x+
bx ,
b1 -
x.
b1 %
b10 &
b100 '
x$
1*
0)
0(
$end
#5
1!
1(
b1 ,
0+
1.
0$
b10 -
#10
0!
0(
#15
1!
1(
b10 ,
#20
1"
0!
1)
0(
b1 ,
#25
1!
1(
#30
0!
0(
#35
1!
1(
#40
0"
0!
0)
0(
b10 ,
#45
1!
1(
#50
0#
0!
0*
0(
b100 -
#55
1!
1(
b100 ,
0.
b1 -
#60
0!
0(
#65
1!
1(
b1 ,
1+
1$
#70
1#
0!
1*
0(
b10 -
#75
1!
1(
b10 ,
0+
1.
0$
#80
0!
0(
#85
1!
1(
#90
0#
0!
0*
0(
b100 -
#95
1!
1(
b100 ,
0.
b1 -
#100
0!
0(
#105
1!
1(
b1 ,
1+
1$
#110
0!
0(
#115
1!
1(
0+
0$
#120
1#
0!
1*
0(
b10 -
#125
1!
1(
b10 ,
1.
#130
0!
0(
#135
1!
1(
#140
0!
0(
#145
1!
1(
#150
0!
0(
#155
1!
1(
#160
1"
0!
1)
0(
b1 ,
#165
1!
1(
#170
0#
0!
0*
0(
b1 -
#175
1!
1(
#180
0!
0(
#185
1!
1(
#190
0!
0(
#195
1!
1(
#200
1#
0"
0!
1*
0)
0(
b10 -
#205
1!
1(
b10 ,
