Sequential Design/Assignment-2/Code/Question4/d_ff.v

module d_ff (input clk, rst, d, output reg q);

always @(posedge clk or posedge rst) begin
    if (rst)
    q <= 1'b0;
    else
    q <= d;
end
    
endmodule

Sequential Design/Assignment-2/Code/Question4/d_ff2.v

module d_ff2 (input clk, rst, d, output reg q);

always @(posedge clk or posedge rst) begin
    if (rst)
    //LSB = 1 for 1-Hot Encoding
    q <= 1'b1;
    else
    q <= d;
end
    
endmodule

Sequential Design/Assignment-2/Code/Question4/pulse_detector.v


    module pulse_detector (input clk, rst, x, output reg y);

    wire Qa, Qb, Qc, Da, Db, Dc;

    d_ff2 A (.d(Da), .clk(clk), .rst(rst), .q(Qa));
    d_ff  B (.d(Db), .clk(clk), .rst(rst), .q(Qb));
    d_ff  C (.d(Dc), .clk(clk), .rst(rst), .q(Qc));

    assign Da = ((~Qb & ~x) | Qc);
    assign Db = ~Qc & x;
    assign Dc = Qb & ~x;

    assign y = Qc;

    endmodule

Sequential Design/Assignment-2/Code/Question4/tb_pulse_detector.v
module tb_pulse_detector;

reg clk, rst, x;
wire y;

pulse_detector m0 (.clk(clk), .rst(rst), .x(x), .y(y));

always #5 clk = ~clk;

initial begin
    clk = 0;
    rst = 0;
end

initial begin
    $dumpvars;
    
    @(posedge clk);
    rst = 1;

    repeat(4) @(posedge clk);

    rst = 0;

    $display("Check the Output after reset");
    if (y !=0 ) begin
        $display("Incorrect Output after reset");
    end
    
    @(posedge clk);
    x = 1;

    repeat(3) @(posedge clk);
    x = 0;

    repeat(2) @(negedge clk);
    if (y != 1) begin
        @(negedge clk);
        if (y != 0) begin
            $display("Incorrect Output");
            $finish;
        end
    end

    @(posedge clk);
    x = 1;

    repeat(5) @(posedge clk);
    x = 0;

    repeat(2) @(negedge clk);
    if (y != 1) begin
        @(negedge clk);
        if (y != 0) begin
            $display("Incorrect Output");
            $finish;
        end
    end


    repeat(10) @(posedge clk);
    $display("All Test Cases Passed!");
    $finish;
end
endmodule

Sequential Design/Assignment-2/Code/Question4/dump.vcd
$date
	Sat Jul 27 15:57:58 2024
$end
$version
	ModelSim Version 2020.1
$end
$timescale
	1ps
$end

$scope module tb_pulse_detector $end
$var reg 1 ! clk $end
$var reg 1 " rst $end
$var reg 1 # x $end
$var wire 1 $ y $end

$scope module m0 $end
$var wire 1 % clk $end
$var wire 1 & rst $end
$var wire 1 ' x $end
$var reg 1 ( y $end
$var wire 1 ) Qa $end
$var wire 1 * Qb $end
$var wire 1 + Qc $end
$var wire 1 , Da $end
$var wire 1 - Db $end
$var wire 1 . Dc $end

$scope module A $end
$var wire 1 % clk $end
$var wire 1 & rst $end
$var wire 1 , d $end
$var reg 1 / q $end
$upscope $end

$scope module B $end
$var wire 1 % clk $end
$var wire 1 & rst $end
$var wire 1 - d $end
$var reg 1 0 q $end
$upscope $end

$scope module C $end
$var wire 1 % clk $end
$var wire 1 & rst $end
$var wire 1 . d $end
$var reg 1 1 q $end
$upscope $end
$upscope $end
$upscope $end
$enddefinitions $end
#0
$dumpvars
0!
0"
x#
x(
x/
x0
x1
x$
x)
x*
x+
x,
x-
x.
x'
0&
0%
$end
#5
1!
1%
1"
1&
1/
00
01
1)
0*
0+
0.
0(
0$
#10
0!
0%
#15
1!
1%
#20
0!
0%
#25
1!
1%
#30
0!
0%
#35
1!
1%
#40
0!
0%
#45
1!
1%
0"
0&
#50
0!
0%
#55
1!
1%
1#
1'
0,
1-
x/
x0
x)
x*
#60
0!
0%
#65
1!
1%
0/
10
0)
1*
#70
0!
0%
#75
1!
1%
#80
0!
0%
#85
1!
1%
0#
0'
0-
1.
#90
0!
0%
#95
1!
1%
00
11
0*
1+
1,
0.
1(
1$
#100
0!
0%
#105
1!
1%
1#
1'
1/
01
1)
0+
0,
1-
0(
0$
#110
0!
0%
#115
1!
1%
0/
10
0)
1*
#120
0!
0%
#125
1!
1%
#130
0!
0%
#135
1!
1%
#140
0!
0%
#145
1!
1%
#150
0!
0%
#155
1!
1%
0#
0'
0-
1.
#160
0!
0%
#165
1!
1%
00
11
0*
1+
1,
0.
1(
1$
#170
0!
0%
#175
1!
1%
1/
01
1)
0+
0(
0$
