Sequential Design/Assignment-1/Code/Question4/t_ff.v

module t_ff (input T, clk, rst, output reg Q);

always @(posedge clk or posedge rst) begin
    if (rst)
    Q <= 0;
    else if (T)
    Q <= ~Q;
end
endmodule

Sequential Design/Assignment-1/Code/Question4/freq_divider.v


    module freq_divider (input clk, rst, output reg y);

    wire Qa, Qb, Qc, Qd;
    wire Tb, Tc, Td;

    t_ff A(.T(1'b1), .clk(clk), .rst(rst), .Q(Qa));
    t_ff B(.T(Tb), .clk(clk), .rst(rst), .Q(Qb));
    t_ff C(.T(Tc), .clk(clk), .rst(rst), .Q(Qc));
    t_ff D(.T(Td), .clk(clk), .rst(rst), .Q(Qd));

    assign Tb = Qa & ~Qd;
    assign Tc = Qb & Qa;
    assign Td = Qa & (Qd | (Qc & Qb));

    assign y = (Qd & ~Qc) | (Qa & Qc) | (Qb & Qc);


    endmodule

Sequential Design/Assignment-1/Code/Question4/tb_freq_divider.v
//`timescale 1ns/1ns

module tb_freq_divider;
    reg clk, rst;
    wire y;

    freq_divider m1 (
        .clk(clk),
        .rst(rst),
        .y(y)
    );

    initial begin
        $dumpvars;
        clk = 0;
        rst = 0;
    end

    always #5 clk = ~clk; // clock generator

    initial begin
        
        rst = 0;
        @(posedge clk);

        rst = 1;
        repeat (5) @(posedge clk);

        if (y != 0) begin
            $display("Initial Output is Incorrect");
        end
        rst = 0;

        // Test sequence
        repeat (6) @(posedge clk);
        
        if (y != 1) begin
            $display("Failed to divide the frequency by 10 after reset");
        end
        repeat (30) @(posedge clk);

        rst = 1;
        repeat (3) @(posedge clk);
        if (y != 0) begin
            $display("Error: Output is Incorrect");
        end

        rst = 0;

        repeat (5.5) @(posedge clk); 
        //@(negedge clk);
        if (y != 1) begin
            $display("Failed to divide the frequency by 10 after reset");
            $finish;
        end
        repeat (22) @(posedge clk);

        $display("All test cases Passed");

        $finish;
    end
endmodule

Sequential Design/Assignment-1/Code/Question4/dump.vcd
$date
	Fri Jul 26 18:23:02 2024
$end
$version
	ModelSim Version 2020.1
$end
$timescale
	1ps
$end

$scope module tb_freq_divider $end
$var reg 1 ! clk $end
$var reg 1 " rst $end
$var wire 1 # y $end

$scope module m1 $end
$var wire 1 $ clk $end
$var wire 1 % rst $end
$var reg 1 & y $end
$var wire 1 ' Qa $end
$var wire 1 ( Qb $end
$var wire 1 ) Qc $end
$var wire 1 * Qd $end
$var wire 1 + Tb $end
$var wire 1 , Tc $end
$var wire 1 - Td $end

$scope module A $end
$var wire 1 . T $end
$var wire 1 $ clk $end
$var wire 1 % rst $end
$var reg 1 / Q $end
$upscope $end

$scope module B $end
$var wire 1 + T $end
$var wire 1 $ clk $end
$var wire 1 % rst $end
$var reg 1 0 Q $end
$upscope $end

$scope module C $end
$var wire 1 , T $end
$var wire 1 $ clk $end
$var wire 1 % rst $end
$var reg 1 1 Q $end
$upscope $end

$scope module D $end
$var wire 1 - T $end
$var wire 1 $ clk $end
$var wire 1 % rst $end
$var reg 1 2 Q $end
$upscope $end
$upscope $end
$upscope $end
$enddefinitions $end
#0
$dumpvars
0!
0"
x&
x/
x0
x1
x2
x#
x'
x(
x)
x*
x+
x,
x-
0%
0$
1.
$end
#5
1!
1$
1"
1%
0/
00
01
02
0'
0(
0)
0*
0+
0,
0-
0&
0#
#10
0!
0$
#15
1!
1$
#20
0!
0$
#25
1!
1$
#30
0!
0$
#35
1!
1$
#40
0!
0$
#45
1!
1$
#50
0!
0$
#55
1!
1$
0"
0%
#60
0!
0$
#65
1!
1$
1/
1'
1+
#70
0!
0$
#75
1!
1$
0/
10
0'
1(
0+
#80
0!
0$
#85
1!
1$
1/
1'
1+
1,
#90
0!
0$
#95
1!
1$
0/
00
11
0'
0(
1)
0+
0,
#100
0!
0$
#105
1!
1$
1/
1'
1+
1&
1#
#110
0!
0$
#115
1!
1$
0/
10
0'
1(
0+
#120
0!
0$
#125
1!
1$
1/
1'
1+
1,
1-
#130
0!
0$
#135
1!
1$
0/
00
01
12
0'
0(
0)
1*
0+
0,
0-
#140
0!
0$
#145
1!
1$
1/
1'
1-
#150
0!
0$
#155
1!
1$
0/
02
0'
0*
0-
0&
0#
#160
0!
0$
#165
1!
1$
1/
1'
1+
#170
0!
0$
#175
1!
1$
0/
10
0'
1(
0+
#180
0!
0$
#185
1!
1$
1/
1'
1+
1,
#190
0!
0$
#195
1!
1$
0/
00
11
0'
0(
1)
0+
0,
#200
0!
0$
#205
1!
1$
1/
1'
1+
1&
1#
#210
0!
0$
#215
1!
1$
0/
10
0'
1(
0+
#220
0!
0$
#225
1!
1$
1/
1'
1+
1,
1-
#230
0!
0$
#235
1!
1$
0/
00
01
12
0'
0(
0)
1*
0+
0,
0-
#240
0!
0$
#245
1!
1$
1/
1'
1-
#250
0!
0$
#255
1!
1$
0/
02
0'
0*
0-
0&
0#
#260
0!
0$
#265
1!
1$
1/
1'
1+
#270
0!
0$
#275
1!
1$
0/
10
0'
1(
0+
#280
0!
0$
#285
1!
1$
1/
1'
1+
1,
#290
0!
0$
#295
1!
1$
0/
00
11
0'
0(
1)
0+
0,
#300
0!
0$
#305
1!
1$
1/
1'
1+
1&
1#
#310
0!
0$
#315
1!
1$
0/
10
0'
1(
0+
#320
0!
0$
#325
1!
1$
1/
1'
1+
1,
1-
#330
0!
0$
#335
1!
1$
0/
00
01
12
0'
0(
0)
1*
0+
0,
0-
#340
0!
0$
#345
1!
1$
1/
1'
1-
#350
0!
0$
#355
1!
1$
0/
02
0'
0*
0-
0&
0#
#360
0!
0$
#365
1!
1$
1/
1'
1+
#370
0!
0$
#375
1!
1$
0/
10
0'
1(
0+
#380
0!
0$
#385
1!
1$
1/
1'
1+
1,
#390
0!
0$
#395
1!
1$
0/
00
11
0'
0(
1)
0+
0,
#400
0!
0$
#405
1!
1$
1/
1'
1+
1&
1#
#410
0!
0$
#415
1!
1$
1"
1%
0/
10
00
01
0'
0)
0+
0&
0#
#420
0!
0$
#425
1!
1$
#430
0!
0$
#435
1!
1$
#440
0!
0$
#445
1!
1$
0"
0%
#450
0!
0$
#455
1!
1$
1/
1'
1+
#460
0!
0$
#465
1!
1$
0/
10
0'
1(
0+
#470
0!
0$
#475
1!
1$
1/
1'
1+
1,
#480
0!
0$
#485
1!
1$
0/
00
11
0'
0(
1)
0+
0,
#490
0!
0$
#495
1!
1$
1/
1'
1+
1&
1#
#500
0!
0$
#505
1!
1$
0/
10
0'
1(
0+
#510
0!
0$
#515
1!
1$
1/
1'
1+
1,
1-
#520
0!
0$
#525
1!
1$
0/
00
01
12
0'
0(
0)
1*
0+
0,
0-
#530
0!
0$
#535
1!
1$
1/
1'
1-
#540
0!
0$
#545
1!
1$
0/
02
0'
0*
0-
0&
0#
#550
0!
0$
#555
1!
1$
1/
1'
1+
#560
0!
0$
#565
1!
1$
0/
10
0'
1(
0+
#570
0!
0$
#575
1!
1$
1/
1'
1+
1,
#580
0!
0$
#585
1!
1$
0/
00
11
0'
0(
1)
0+
0,
#590
0!
0$
#595
1!
1$
1/
1'
1+
1&
1#
#600
0!
0$
#605
1!
1$
0/
10
0'
1(
0+
#610
0!
0$
#615
1!
1$
1/
1'
1+
1,
1-
#620
0!
0$
#625
1!
1$
0/
00
01
12
0'
0(
0)
1*
0+
0,
0-
#630
0!
0$
#635
1!
1$
1/
1'
1-
#640
0!
0$
#645
1!
1$
0/
02
0'
0*
0-
0&
0#
#650
0!
0$
#655
1!
1$
1/
1'
1+
#660
0!
0$
#665
1!
1$
0/
10
0'
1(
0+
#670
0!
0$
#675
1!
1$
1/
1'
1+
1,
#680
0!
0$
#685
1!
1$
0/
00
11
0'
0(
1)
0+
0,
#690
0!
0$
#695
1!
1$
1/
1'
1+
1&
1#
#700
0!
0$
#705
1!
1$
0/
10
0'
1(
0+
#710
0!
0$
#715
1!
1$
1/
1'
1+
1,
1-
