Sequential Design/Assignment-1/Code/Question4/freq_divider.v


    module freq_divider (input clk, rst, output reg y);

    reg [3:0] state;
    localparam S0 = 4'd0;
    localparam S1 = 4'd1;
    localparam S2 = 4'd2;
    localparam S3 = 4'd3;
    localparam S4 = 4'd4;
    localparam S5 = 4'd5;
    localparam S6 = 4'd6;
    localparam S7 = 4'd7;
    localparam S8 = 4'd8;
    localparam S9 = 4'd9;

    always @(posedge clk or posedge rst) 
    begin
    if (rst)
    state <= S0;
    else
    state <= state;    
    end

    always @(posedge clk or posedge rst) 
    begin
    case (state)
    S0 : state <= S1;
    S1 : state <= S2;
    S2 : state <= S3;
    S3 : state <= S4;
    S4 : state <= S5;
    S5 : state <= S6;
    S6 : state <= S7;
    S7 : state <= S8;
    S8 : state <= S9;
    S9 : state <= S0;
    endcase    
    end

    always @(state) 
    begin
    case (state)
    S0 : y <= 1;
    S1 : y <= 0;
    S2 : y <= 0;
    S3 : y <= 0;
    S4 : y <= 0;
    S5 : y <= 0;
    S6 : y <= 0;
    S7 : y <= 0;
    S8 : y <= 0;
    S9 : y <= 0;
    endcase    
    end
    endmodule

Sequential Design/Assignment-1/Code/Question4/tb_freq_divider.v


    module tb_freq_divider;
    reg clk, rst;
    wire y;

    freq_divider m1 (.clk(clk), .rst(rst), .y(y));

    always #5 clk = ~clk;
    
    initial begin
    $dumpvars;

    clk = 0;
    rst = 0;
    #5;

    rst = 1;
    #10;

    rst = 0;
    #10;

    #250;
    $finish;
    end
    endmodule

Sequential Design/Assignment-1/Code/Question4/dump.vcd
$date
	Mon Jul 15 15:06:18 2024
$end
$version
	ModelSim Version 2020.1
$end
$timescale
	1ps
$end

$scope module tb_freq_divider $end
$var reg 1 ! clk $end
$var reg 1 " rst $end
$var wire 1 # y $end

$scope module m1 $end
$var parameter 4 $ S0 $end
$var parameter 4 % S1 $end
$var parameter 4 & S2 $end
$var parameter 4 ' S3 $end
$var parameter 4 ( S4 $end
$var parameter 4 ) S5 $end
$var parameter 4 * S6 $end
$var parameter 4 + S7 $end
$var parameter 4 , S8 $end
$var parameter 4 - S9 $end
$var wire 1 . clk $end
$var wire 1 / rst $end
$var reg 1 0 y $end
$var reg 4 1 state [3:0] $end
$upscope $end
$upscope $end
$enddefinitions $end
#0
$dumpvars
0!
0"
x0
bx 1
b0 $
b1 %
b10 &
b11 '
b100 (
b101 )
b110 *
b111 +
b1000 ,
b1001 -
x#
0/
0.
$end
#5
1!
1"
1.
1/
b0 1
10
1#
#10
0!
0.
#15
0"
1!
0/
1.
b1 1
00
0#
#20
0!
0.
#25
1!
1.
b10 1
#30
0!
0.
#35
1!
1.
b11 1
#40
0!
0.
#45
1!
1.
b100 1
#50
0!
0.
#55
1!
1.
b101 1
#60
0!
0.
#65
1!
1.
b110 1
#70
0!
0.
#75
1!
1.
b111 1
#80
0!
0.
#85
1!
1.
b1000 1
#90
0!
0.
#95
1!
1.
b1001 1
#100
0!
0.
#105
1!
1.
b0 1
10
1#
#110
0!
0.
#115
1!
1.
b1 1
00
0#
#120
0!
0.
#125
1!
1.
b10 1
#130
0!
0.
#135
1!
1.
b11 1
#140
0!
0.
#145
1!
1.
b100 1
#150
0!
0.
#155
1!
1.
b101 1
#160
0!
0.
#165
1!
1.
b110 1
#170
0!
0.
#175
1!
1.
b111 1
#180
0!
0.
#185
1!
1.
b1000 1
#190
0!
0.
#195
1!
1.
b1001 1
#200
0!
0.
#205
1!
1.
b0 1
10
1#
#210
0!
0.
#215
1!
1.
b1 1
00
0#
#220
0!
0.
#225
1!
1.
b10 1
#230
0!
0.
#235
1!
1.
b11 1
#240
0!
0.
#245
1!
1.
b100 1
#250
0!
0.
#255
1!
1.
b101 1
#260
0!
0.
#265
1!
1.
b110 1
