Sequential Design/Assignment-2/Code/Question5/d_ff.v
module d_ff (input clk, rst, d, output reg q);

always @(posedge clk or posedge rst) begin
    if (rst)
        q <= 1'b0;
    else
        q <= d;
end
endmodule

Sequential Design/Assignment-2/Code/Question5/synchronizer.v


    module synchronizer (input clk_A, clk_B, rst_A, rst, output reg rst_B);

    wire w0, w1, w2;

    d_ff m0 (.clk(clk_A), .rst(rst), .d(rst_A), .q(w0));

    //Two Flops Synchronizer
    d_ff m1 (.clk(clk_B), .rst(1'b0), .d(w0), .q(w1));
    d_ff m2 (.clk(clk_B), .rst(1'b0), .d(w1), .q(w2));

    assign rst_B = w2;
        
    endmodule

Sequential Design/Assignment-2/Code/Question5/tb_synchronizer.v

    module tb_synchronizer;
    reg clk_A, clk_B, rst, rst_A;
    wire rst_B;

    synchronizer dut (.clk_A(clk_A), .clk_B(clk_B), .rst(rst), .rst_A(rst_A), .rst_B(rst_B));

    always #5 clk_A = ~clk_A;
    always #20 clk_B = ~clk_B;

    initial begin
        $dumpvars;

        clk_A = 0;
        clk_B = 0;
        rst = 0;
        rst_A = 0;

        #20;

        rst = 1;
        #10;
        rst_A = 1;
        #40;

        rst = 0;
        #40;

        rst_A = 0;
        #80;

        rst_A = 1;
        #20;

        rst_A = 0;
        #30;

        rst_A = 1;
        #30;

        rst_A = 0;
        #100;

        $finish;
    
    end     
    endmodule

Sequential Design/Assignment-2/Code/Question5/dump.vcd
$date
	Fri Jul 19 16:06:24 2024
$end
$version
	ModelSim Version 2020.1
$end
$timescale
	1ps
$end

$scope module tb_synchronizer $end
$var reg 1 ! clk_A $end
$var reg 1 " clk_B $end
$var reg 1 # rst $end
$var reg 1 $ rst_A $end
$var wire 1 % rst_B $end

$scope module dut $end
$var wire 1 & clk_A $end
$var wire 1 ' clk_B $end
$var wire 1 ( rst_A $end
$var wire 1 ) rst $end
$var reg 1 * rst_B $end
$var wire 1 + w0 $end
$var wire 1 , w1 $end
$var wire 1 - w2 $end

$scope module m0 $end
$var wire 1 & clk $end
$var wire 1 ) rst $end
$var wire 1 ( d $end
$var reg 1 . q $end
$upscope $end

$scope module m1 $end
$var wire 1 ' clk $end
$var wire 1 / rst $end
$var wire 1 + d $end
$var reg 1 0 q $end
$upscope $end

$scope module m2 $end
$var wire 1 ' clk $end
$var wire 1 1 rst $end
$var wire 1 , d $end
$var reg 1 2 q $end
$upscope $end
$upscope $end
$upscope $end
$enddefinitions $end
#0
$dumpvars
0!
0"
0#
0$
x*
x.
x0
x2
x%
x+
x,
x-
0(
0)
0'
0&
01
0/
$end
#5
1!
1&
0.
0+
#10
0!
0&
#15
1!
1&
#20
1"
1#
0!
1'
1)
0&
00
0,
#25
1!
1&
#30
1$
0!
1(
0&
#35
1!
1&
#40
0"
0!
0'
0&
#45
1!
1&
#50
0!
0&
#55
1!
1&
#60
1"
0!
1'
0&
02
0-
0*
0%
#65
1!
1&
#70
0#
0!
0)
0&
#75
1!
1&
1.
1+
#80
0"
0!
0'
0&
#85
1!
1&
#90
0!
0&
#95
1!
1&
#100
1"
0!
1'
0&
10
1,
#105
1!
1&
#110
0$
0!
0(
0&
#115
1!
1&
0.
0+
#120
0"
0!
0'
0&
#125
1!
1&
#130
0!
0&
#135
1!
1&
#140
1"
0!
1'
0&
00
12
0,
1-
1*
1%
#145
1!
1&
#150
0!
0&
#155
1!
1&
#160
0"
0!
0'
0&
#165
1!
1&
#170
0!
0&
#175
1!
1&
#180
1"
0!
1'
0&
02
0-
0*
0%
#185
1!
1&
#190
1$
0!
1(
0&
#195
1!
1&
1.
1+
#200
0"
0!
0'
0&
#205
1!
1&
#210
0$
0!
0(
0&
#215
1!
1&
0.
0+
#220
1"
0!
1'
0&
#225
1!
1&
#230
0!
0&
#235
1!
1&
#240
1$
0"
0!
1(
0'
0&
#245
1!
1&
1.
1+
#250
0!
0&
#255
1!
1&
#260
1"
0!
1'
0&
10
1,
#265
1!
1&
#270
0$
0!
0(
0&
#275
1!
1&
0.
0+
#280
0"
0!
0'
0&
#285
1!
1&
#290
0!
0&
#295
1!
1&
#300
1"
0!
1'
0&
00
12
0,
1-
1*
1%
#305
1!
1&
#310
0!
0&
#315
1!
1&
#320
0"
0!
0'
0&
#325
1!
1&
#330
0!
0&
#335
1!
1&
#340
1"
0!
1'
0&
02
0-
0*
0%
