FIFO Design/Code/fifo.v
module fifo #(parameter DATA_SIZE = 8, parameter ADDRESS_SIZE = 3)
             (input clk, rst, push, pop,
              input [DATA_SIZE-1:0] data_in,
              output reg [DATA_SIZE-1:0] data_out,
              output reg full, empty,
              output reg overflow, underflow);

    localparam ADDRESS_DEPTH = 2**ADDRESS_SIZE;
    reg [DATA_SIZE-1:0] memory [ADDRESS_DEPTH-1:0];
    reg [ADDRESS_SIZE-1:0] read_ptr, write_ptr;
    reg [ADDRESS_SIZE:0] status; // Extra bit for distinguishing full and empty

    integer i;

    //Empty & Full Logic
    assign empty = (status == 0);
    assign full = (status == ADDRESS_DEPTH);
  
    // Overflow & Underflow Logic
    assign overflow = (push && full);
    assign underflow = (pop && empty); 


    // Sequential logic for write and pointer updates
    always @(posedge clk or negedge rst) begin
    if (!rst) begin
        // Reset logic
        read_ptr <= 0;
        write_ptr <= 0;
        status <= 0;
        for (i = 0; i < ADDRESS_DEPTH; i = i + 1) begin
            memory[i] <= {DATA_SIZE{1'b0}};
        end
    end else begin
        if (push && pop) begin
            // If both push and pop occur at the same time
            if (!full && !empty) 
            begin
                memory[write_ptr] <= data_in; // Perform write
                write_ptr <= write_ptr + 1;
                read_ptr <= read_ptr + 1;
            end
            else if (full) begin
                read_ptr <= read_ptr + 1;
                status <= status - 1;
            end
            else if (empty) begin
                memory[write_ptr] <= data_in;
                write_ptr <= write_ptr + 1;
                status <= status + 1;
            end
        end else if (push && !full) begin
            memory[write_ptr] <= data_in; 
            write_ptr <= write_ptr + 1;
            status <= status + 1;
        end else if (pop && !empty) begin
            read_ptr <= read_ptr + 1;
            status <= status - 1;
        end
    end
end

    // Combinational logic for immediate read
    always @(*) begin
        if (push && pop) begin
            if (!full && !empty) 
            begin
                data_out = memory[read_ptr];  // Perform read
            end
            else if (full) begin
                data_out = memory[read_ptr];
            end
            end
        else if (pop && !empty ) begin
            data_out = memory[read_ptr]; // Perform read immediately
        end else begin
            data_out = 8'b0; // 0 value when pop is not active or FIFO is empty
        end
    end

endmodule

FIFO Design/Code/tb_fifo.v

module tb_fifo;

    // Parameters
    parameter DATA_SIZE = 8;
    parameter ADDRESS_SIZE = 3;
    localparam ADDRESS_DEPTH = 2**ADDRESS_SIZE;

    // Signals
    reg clk, rst, push, pop;
    reg [DATA_SIZE-1:0] data_in;
    wire [DATA_SIZE-1:0] data_out;
    wire full, empty, overflow, underflow;
    integer i;

    // Instantiation
    fifo #(DATA_SIZE, ADDRESS_SIZE) uut (
        .clk(clk),
        .rst(rst),
        .push(push),
        .pop(pop),
        .data_in(data_in),
        .data_out(data_out),
        .full(full),
        .empty(empty),
        .overflow(overflow),
        .underflow(underflow)
    );

    // Clock generation
    always #5 clk = ~clk;

    // Testbench logic
    initial begin
        $dumpvars;

        // Initialize signals
        clk = 0;
        rst = 1;
        push = 0;
        pop = 0;
        data_in = 0;

        // Reset the FIFO
        @(posedge clk);
        rst = 0;
        @(posedge clk);
        rst = 1;
        @(posedge clk);

        // Test case: Pushing until Full
        $display("Test case: Pushing Until full");
        for (i = 0; i < ADDRESS_DEPTH; i = i + 1) begin
            @(posedge clk);
            push = 1;
            data_in = i;
        end
        @(posedge clk);
        push = 0;

        @(negedge clk);
        if (!full) $display("Error: FIFO should be full");
        else $display("Passed");

        // Test case: Popping until empty
        $display("Test case: Popping Until empty");
        for (i = 0; i < ADDRESS_DEPTH; i = i + 1) begin
            @(posedge clk);
            pop = 1;
            @(negedge clk);
            if (data_out != i) $display("Error: FIFO data mismatch. Expected %d, Got %d", i, data_out);
        end
        @(posedge clk);
        pop = 0;

        @(negedge clk);
        if (!empty) $display("Error: FIFO should be empty");
        else $display("Passed");

        // Test case: Simultaneous push and pop
        $display("Test case: Simultaneous push and pop");
        for (i = 0; i < ADDRESS_DEPTH; i = i + 1) begin
            @(posedge clk);
            push = 1;
            pop = 1;
            data_in = i;
            repeat(2) @(posedge clk);
            if (data_out != i) $display("Error: FIFO data mismatch. Expected %0d, Got %0d", i, data_out);
        end
        @(posedge clk); 
        push = 0;
        pop = 0;

        // Test Overflow
        $display("Test Case: Overflow Detection");
        for (i = 0; i < ADDRESS_DEPTH; i = i + 1) begin
            @(posedge clk);
            push = 1;
            data_in = i;
        end

        @(negedge clk);
        if (!overflow) $display("Error: FIFO should have Overflowed");
        else $display("Passed");
        @(posedge clk) push = 0;
        @(posedge clk);
        pop = 0;

        // Test Case: Underflow Detection
        $display("Test Case: Underflow Detection");

        // First, empty the FIFO completely
        for (i = 0; i < ADDRESS_DEPTH; i = i + 1) begin
            @(posedge clk);
            pop = 1;
        end

        @(posedge clk);
        pop = 0; // Ensure pop is deasserted before testing underflow

        // Now, perform extra pops to cause underflow
        for (i = 0; i < 5; i = i + 1) begin
            @(posedge clk);
            pop = 1;
        end
        
        @(negedge clk);
        if (!underflow) $display("Error: FIFO should have underflowed");
        else $display("Passed");

        pop = 0;

        repeat(10) @(posedge clk)

        $finish;
    end
endmodule

FIFO Design/Code/dump.vcd
$date
	Thu Aug 15 23:59:43 2024
$end
$version
	ModelSim Version 2020.1
$end
$timescale
	1ps
$end

$scope module tb_fifo $end
$var parameter 32 ! DATA_SIZE $end
$var parameter 32 " ADDRESS_SIZE $end
$var parameter 32 # ADDRESS_DEPTH $end
$var reg 1 $ clk $end
$var reg 1 % rst $end
$var reg 1 & push $end
$var reg 1 ' pop $end
$var reg 8 ( data_in [7:0] $end
$var wire 1 ) data_out [7] $end
$var wire 1 * data_out [6] $end
$var wire 1 + data_out [5] $end
$var wire 1 , data_out [4] $end
$var wire 1 - data_out [3] $end
$var wire 1 . data_out [2] $end
$var wire 1 / data_out [1] $end
$var wire 1 0 data_out [0] $end
$var wire 1 1 full $end
$var wire 1 2 empty $end
$var wire 1 3 overflow $end
$var wire 1 4 underflow $end
$var integer 32 5 i $end

$scope module uut $end
$var parameter 32 6 DATA_SIZE $end
$var parameter 32 7 ADDRESS_SIZE $end
$var parameter 32 8 ADDRESS_DEPTH $end
$var wire 1 9 clk $end
$var wire 1 : rst $end
$var wire 1 ; push $end
$var wire 1 < pop $end
$var wire 1 = data_in [7] $end
$var wire 1 > data_in [6] $end
$var wire 1 ? data_in [5] $end
$var wire 1 @ data_in [4] $end
$var wire 1 A data_in [3] $end
$var wire 1 B data_in [2] $end
$var wire 1 C data_in [1] $end
$var wire 1 D data_in [0] $end
$var reg 8 E data_out [7:0] $end
$var reg 1 F full $end
$var reg 1 G empty $end
$var reg 1 H overflow $end
$var reg 1 I underflow $end
$var reg 3 J read_ptr [2:0] $end
$var reg 3 K write_ptr [2:0] $end
$var reg 4 L status [3:0] $end
$var integer 32 M i $end
$upscope $end
$upscope $end
$enddefinitions $end
#0
$dumpvars
0$
1%
0&
0'
b0 (
b0 E
xF
xG
0H
0I
bx J
bx K
bx L
b1000 !
b11 "
b1000 #
b1000 6
b11 7
b1000 8
bx 5
bx M
00
0/
0.
0-
0,
0+
0*
0)
x1
x2
03
04
0D
0C
0B
0A
0@
0?
0>
0=
0<
0;
1:
09
$end
#5
1$
19
0%
0:
b0 M
b1 M
b10 M
b11 M
b100 M
b101 M
b110 M
b111 M
b1000 M
b0 J
b0 K
b0 L
1G
0F
12
01
#10
0$
09
#15
1$
19
b0 M
b1 M
b10 M
b11 M
b100 M
b101 M
b110 M
b111 M
b1000 M
1%
1:
#20
0$
09
#25
1$
19
b0 5
#30
0$
09
#35
1$
19
1&
b1 5
1;
#40
0$
09
#45
1$
19
b1 (
b10 5
1D
b1 K
b1 L
0G
02
#50
0$
09
#55
1$
19
b10 (
b11 5
0D
1C
b10 K
b10 L
#60
0$
09
#65
1$
19
b11 (
b100 5
1D
b11 K
b11 L
#70
0$
09
#75
1$
19
b100 (
b101 5
0D
0C
1B
b100 K
b100 L
#80
0$
09
#85
1$
19
b101 (
b110 5
1D
b101 K
b101 L
#90
0$
09
#95
1$
19
b110 (
b111 5
0D
1C
b110 K
b110 L
#100
0$
09
#105
1$
19
b111 (
b1000 5
1D
b111 K
b111 L
#110
0$
09
#115
1$
19
0&
0;
b0 K
b1000 L
1F
11
#120
0$
09
b0 5
#125
1$
19
1'
1<
#130
0$
09
b1 5
#135
1$
19
b1 J
b111 L
0F
01
b1 E
10
#140
0$
09
b10 5
#145
1$
19
b10 J
b110 L
b10 E
00
1/
#150
0$
09
b11 5
#155
1$
19
b11 J
b101 L
b11 E
10
#160
0$
09
b100 5
#165
1$
19
b100 J
b100 L
b100 E
00
0/
1.
#170
0$
09
b101 5
#175
1$
19
b101 J
b11 L
b101 E
10
#180
0$
09
b110 5
#185
1$
19
b110 J
b10 L
b110 E
00
1/
#190
0$
09
b111 5
#195
1$
19
b111 J
b1 L
b111 E
10
#200
0$
09
b1000 5
#205
1$
19
0'
0<
b0 E
00
0/
0.
b0 J
b0 L
1G
12
#210
0$
09
b0 5
#215
1$
19
1&
1'
b0 (
0D
0C
0B
1;
1<
1I
14
#220
0$
09
#225
1$
19
b1 K
b1 L
0G
0I
02
04
#230
0$
09
#235
1$
19
b1 5
b10 K
b1 J
#240
0$
09
#245
1$
19
b1 (
1D
b11 K
b10 J
#250
0$
09
#255
1$
19
b100 K
b11 J
b1 E
10
#260
0$
09
#265
1$
19
b10 5
b101 K
b100 J
#270
0$
09
#275
1$
19
b10 (
0D
1C
b110 K
b101 J
#280
0$
09
#285
1$
19
b111 K
b110 J
b10 E
00
1/
#290
0$
09
#295
1$
19
b11 5
b0 K
b111 J
#300
0$
09
#305
1$
19
b11 (
1D
b1 K
b0 J
#310
0$
09
#315
1$
19
b10 K
b1 J
b11 E
10
#320
0$
09
#325
1$
19
b100 5
b11 K
b10 J
#330
0$
09
#335
1$
19
b100 (
0D
0C
1B
b100 K
b11 J
#340
0$
09
#345
1$
19
b101 K
b100 J
b100 E
00
0/
1.
#350
0$
09
#355
1$
19
b101 5
b110 K
b101 J
#360
0$
09
#365
1$
19
b101 (
1D
b111 K
b110 J
#370
0$
09
#375
1$
19
b0 K
b111 J
b101 E
10
#380
0$
09
#385
1$
19
b110 5
b1 K
b0 J
#390
0$
09
#395
1$
19
b110 (
0D
1C
b10 K
b1 J
#400
0$
09
#405
1$
19
b11 K
b10 J
b110 E
00
1/
#410
0$
09
#415
1$
19
b111 5
b100 K
b11 J
#420
0$
09
#425
1$
19
b111 (
1D
b101 K
b100 J
#430
0$
09
#435
1$
19
b110 K
b101 J
b111 E
10
#440
0$
09
#445
1$
19
b1000 5
b111 K
b110 J
#450
0$
09
#455
1$
19
0&
0'
b0 5
0;
0<
b0 E
00
0/
0.
b0 K
b111 J
#460
0$
09
#465
1$
19
1&
b0 (
b1 5
0D
0C
0B
1;
#470
0$
09
#475
1$
19
b1 (
b10 5
1D
b1 K
b10 L
#480
0$
09
#485
1$
19
b10 (
b11 5
0D
1C
b10 K
b11 L
#490
0$
09
#495
1$
19
b11 (
b100 5
1D
b11 K
b100 L
#500
0$
09
#505
1$
19
b100 (
b101 5
0D
0C
1B
b100 K
b101 L
#510
0$
09
#515
1$
19
b101 (
b110 5
1D
b101 K
b110 L
#520
0$
09
#525
1$
19
b110 (
b111 5
0D
1C
b110 K
b111 L
#530
0$
09
#535
1$
19
b111 (
b1000 5
1D
b111 K
b1000 L
1F
1H
11
13
#540
0$
09
#545
1$
19
0&
0;
0H
03
#550
0$
09
#555
1$
19
b0 5
#560
0$
09
#565
1$
19
1'
b1 5
1<
b111 E
10
1/
1.
#570
0$
09
#575
1$
19
b10 5
b0 J
b111 L
0F
01
b0 E
00
0/
0.
#580
0$
09
#585
1$
19
b11 5
b1 J
b110 L
b1 E
10
#590
0$
09
#595
1$
19
b100 5
b10 J
b101 L
b10 E
00
1/
#600
0$
09
#605
1$
19
b101 5
b11 J
b100 L
b11 E
10
#610
0$
09
#615
1$
19
b110 5
b100 J
b11 L
b100 E
00
0/
1.
#620
0$
09
#625
1$
19
b111 5
b101 J
b10 L
b101 E
10
#630
0$
09
#635
1$
19
b1000 5
b110 J
b1 L
b110 E
00
1/
#640
0$
09
#645
1$
19
0'
b0 5
0<
b0 E
0/
0.
b111 J
b0 L
1G
12
#650
0$
09
#655
1$
19
1'
b1 5
1<
1I
14
#660
0$
09
#665
1$
19
b10 5
#670
0$
09
#675
1$
19
b11 5
#680
0$
09
#685
1$
19
b100 5
#690
0$
09
#695
1$
19
b101 5
#700
0$
09
0'
0<
0I
04
