Sequential Design/Assignment-1/Code/Question1/t_ff.v
    module t_ff (input t, clk, rst, output reg q);

    always @(posedge clk or posedge rst) 
    begin
        if (rst)
            q <= 1'b0;
        else if (t) 
           q <= ~q;
    end
    endmodule

Sequential Design/Assignment-1/Code/Question1/toggle_circuit.v

module toggle_circuit (input button, clk, rst, output y);

wire Q;

t_ff m0(.t(button), .clk(clk), .rst(rst), .q(Q));

assign y = Q;

endmodule

Sequential Design/Assignment-1/Code/Question1/tb_toggle_circuit.v
`timescale 10ns/1ns

module tb_toggle_circuit;

reg button;
reg clk;
reg rst;
wire y;

toggle_circuit uut (
    .button(button),
    .clk(clk),
    .rst(rst),
    .y(y)
);

initial begin
    // Initialize inputs
    button = 0;
    clk = 0;
    rst = 1;
    $dumpvars;

    repeat (5) @(posedge clk);

    // Release reset
    rst = 0;

    // Check initial output
    $display("Checking initial output...");

    if (y != 0) begin
    $display("Error: Initial output is incorrect");
    $finish;
    end

    @(posedge clk)
    // Test button toggle
    $display("Toggling button and checking output...");
    button = 1;
    @(posedge clk);
    if (y != 0) begin
        $display("Error: Output did not toggle on");
        $finish;
    end

    repeat (5) @(posedge clk)
    // Test button toggle again
    $display("Toggling button again and checking output...");
    button = 0;
    repeat(2) @(posedge clk);
    if (y != 0) begin
        $display("Error: Output did not toggle off");
        $finish;
    end

    //Remember State
    $display("Toggling button again and checking output...");
    button = 1;
    @(posedge clk)
    button = 0;
    repeat(2) @(posedge clk);
    if (y != 1) begin
        $display("Error: Output was not remembered");
        $finish;
    end

    // Repeat toggle test 10 times
    $display("Repeating toggle test 10 times...");
    
    repeat (10) button = @(posedge clk) ~button;

    repeat (10) begin
        @(posedge clk);
        if (y != button) begin
            $display("Error: Output did not toggle correctly");
            $finish;
        end
        else
            $display("Tests Passed Successfully");
            $finish;

    end
end
    // Clock generator
    always #10 clk = ~clk;

endmodule

Sequential Design/Assignment-1/Code/Question1/dump.vcd
$date
	Fri Jul 26 11:45:10 2024
$end
$version
	ModelSim Version 2020.1
$end
$timescale
	1ns
$end

$scope module tb_toggle_circuit $end
$var reg 1 ! button $end
$var reg 1 " clk $end
$var reg 1 # rst $end
$var wire 1 $ y $end

$scope module uut $end
$var wire 1 % button $end
$var wire 1 & clk $end
$var wire 1 ' rst $end
$var wire 1 $ y $end
$var wire 1 ( Q $end

$scope module m0 $end
$var wire 1 % t $end
$var wire 1 & clk $end
$var wire 1 ' rst $end
$var reg 1 ) q $end
$upscope $end
$upscope $end
$upscope $end
$enddefinitions $end
#0
$dumpvars
0!
0"
1#
0)
0$
0(
1'
0&
0%
$end
#100
1"
1&
#200
0"
0&
#300
1"
1&
#400
0"
0&
#500
1"
1&
#600
0"
0&
#700
1"
1&
#800
0"
0&
#900
1"
1&
0#
0'
#1000
0"
0&
#1100
1"
1&
1!
1%
#1200
0"
0&
#1300
1"
1&
1)
1(
1$
#1400
0"
0&
#1500
1"
1&
0)
0(
0$
#1600
0"
0&
#1700
1"
1&
1)
1(
1$
#1800
0"
0&
#1900
1"
1&
0)
0(
0$
#2000
0"
0&
#2100
1"
1&
1)
1(
1$
#2200
0"
0&
#2300
1"
1&
0!
0%
0)
0(
0$
#2400
0"
0&
#2500
1"
1&
#2600
0"
0&
#2700
1"
1&
1!
1%
#2800
0"
0&
#2900
1"
1&
0!
0%
1)
1(
1$
#3000
0"
0&
#3100
1"
1&
#3200
0"
0&
#3300
1"
1&
#3400
0"
0&
#3500
1"
1&
1!
1%
#3600
0"
0&
#3700
1"
1&
0!
0%
0)
0(
0$
#3800
0"
0&
#3900
1"
1&
1!
1%
#4000
0"
0&
#4100
1"
1&
0!
0%
1)
1(
1$
#4200
0"
0&
#4300
1"
1&
1!
1%
#4400
0"
0&
#4500
1"
1&
0!
0%
0)
0(
0$
#4600
0"
0&
#4700
1"
1&
1!
1%
#4800
0"
0&
#4900
1"
1&
0!
0%
1)
1(
1$
#5000
0"
0&
#5100
1"
1&
1!
1%
#5200
0"
0&
#5300
1"
1&
0!
0%
0)
0(
0$
