Sequential Design/Assignment-1/Code/Question1/t_ff.v
    module t_ff (input t, clk, rst, output reg q);

    always @(posedge clk or posedge rst) 
    begin
        if (rst)
            q <= 1'b0;
        else if (t) 
           q <= ~q;
        else
            q <= q;
    end
    endmodule

Sequential Design/Assignment-1/Code/Question1/toggle_circuit.v

module toggle_circuit (input button, clk, rst, output reg y);

reg Ta, Tb; 
wire A, B;

t_ff m0(.t(Ta), .clk(clk), .rst(rst), .q(A));
t_ff m1(.t(Tb), .clk(clk), .rst(rst), .q(B));

always @(*)
begin
    assign Ta = (A & button ) | (B & (~button));
    assign Tb = (~A & ~B & button) | (B & ~button);
end

always @(posedge clk or posedge rst) begin
    if (rst)
        begin
        y <= 1'b0;
        Ta <= 0;
        Tb <= 0;
        end
    else if (button)
        y <= B | (A ^ button);
end
endmodule

Sequential Design/Assignment-1/Code/Question1/tb_toggle_circuit.v
`timescale 10ns/1ns

module tb_toggle_circuit;

reg clk, rst, button;
wire y;

toggle_circuit dut (.clk(clk), .rst(rst), .button(button), .y(y));

initial begin
    $dumpvars;

    clk = 0;
    rst = 0;
    
    #20;

    rst = 1;

    #20;
    rst = 0;
    button = 0;

    #10;
    button = 1;

    #20;
    button = 0;

    #20;
    button = 0;

    #20;
    button = 1;

    #10;
    button = 0;

    #30;
    button = 1;

    #10;
    button = 1;

    #10;
    button = 0;

    #30;
    button = 0;

    #25;
    button = 1;

    #10;
    button = 0;

    #20;
    button = 1;
    $finish;

end


initial begin 
    forever #5 clk = ~clk;
end
endmodule

Sequential Design/Assignment-1/Code/Question1/dump.vcd
$date
	Sun Jul 14 16:20:22 2024
$end
$version
	ModelSim Version 2020.1
$end
$timescale
	1ns
$end

$scope module tb_toggle_circuit $end
$var reg 1 ! clk $end
$var reg 1 " rst $end
$var reg 1 # button $end
$var wire 1 $ y $end

$scope module dut $end
$var wire 1 % button $end
$var wire 1 & clk $end
$var wire 1 ' rst $end
$var reg 1 ( y $end
$var reg 1 ) Ta $end
$var reg 1 * Tb $end
$var wire 1 + A $end
$var wire 1 , B $end

$scope module m0 $end
$var wire 1 - t $end
$var wire 1 & clk $end
$var wire 1 ' rst $end
$var reg 1 . q $end
$upscope $end

$scope module m1 $end
$var wire 1 / t $end
$var wire 1 & clk $end
$var wire 1 ' rst $end
$var reg 1 0 q $end
$upscope $end
$upscope $end
$upscope $end
$enddefinitions $end
#0
$dumpvars
0!
0"
x#
x(
x)
x*
x.
x0
x$
x+
x,
x%
0'
0&
x/
x-
$end
#50
1!
1&
#100
0!
0&
#150
1!
1&
#200
1"
0!
1'
0&
0.
00
0(
0)
0*
0$
0-
0/
0+
0,
x*
x/
#250
1!
1&
#300
0!
0&
#350
1!
1&
#400
0"
0#
0!
0'
0%
0&
0*
0/
#450
1!
1&
#500
1#
0!
1%
0&
1*
1/
#550
1!
1&
10
1(
1$
1,
0*
0/
#600
0!
0&
#650
1!
1&
#700
0#
0!
0%
0&
1*
1)
1/
1-
#750
1!
1&
1.
00
1+
0,
0*
0)
0/
0-
#800
0!
0&
#850
1!
1&
#900
0!
0&
#950
1!
1&
#1000
0!
0&
#1050
1!
1&
#1100
1#
0!
1%
0&
1)
1-
#1150
1!
1&
0.
0(
0$
0+
1*
0)
1/
0-
#1200
0#
0!
0%
0&
0*
0/
#1250
1!
1&
#1300
0!
0&
#1350
1!
1&
#1400
0!
0&
#1450
1!
1&
#1500
1#
0!
1%
0&
1*
1/
#1550
1!
1&
10
1(
1$
1,
0*
0/
#1600
0!
0&
#1650
1!
1&
#1700
0#
0!
0%
0&
1*
1)
1/
1-
#1750
1!
1&
1.
00
1+
0,
0*
0)
0/
0-
#1800
0!
0&
#1850
1!
1&
#1900
0!
0&
#1950
1!
1&
#2000
0!
0&
#2050
1!
1&
#2100
0!
0&
#2150
1!
1&
#2200
0!
0&
#2250
1#
1!
1%
1&
1)
1-
0(
0$
#2300
0!
0&
#2350
0#
1!
0%
1&
0)
0-
0.
0+
#2400
0!
0&
#2450
1!
1&
#2500
0!
0&
#2550
1#
