Sequential Design/Design-Problem/Code/d_ff.v


    module d_ff (input d, clk, rst, output reg q);

    always @(posedge clk or posedge rst) begin
       
        if (rst)
            q <= 1'b0;
        else
            q <= d;
    end        
    endmodule

Sequential Design/Design-Problem/Code/counter9.v

    module counter9 (input clk, rst, output [3:0] out);


        wire D_3, D_2, D_1, D_0;
        // D_d = D_3 = Q0' Q3 + Q2 Q1 Q0
        assign D_3 = (~out[0] & out[3]) | (out[2] & out[1] & out[0]);

        // D_c = D_2 = Q2 ^ (Q1 Q0)
        assign D_2 = out[2] ^ (out[1] & out[0]);

        // D_b = D_1 = (Q3' Q1' Q0) + (Q1 Q0')
        assign D_1 = (~out[3] & ~out[1] & out[0]) | (out[1] & ~out[0]);

        // D_a = D_0 = Q0'
        assign D_0 = ~out[0];

        d_ff D (.d(D_3), .clk(clk), .rst(rst), .q(out[3]));
        d_ff C (.d(D_2), .clk(clk), .rst(rst), .q(out[2]));
        d_ff B (.d(D_1), .clk(clk), .rst(rst), .q(out[1]));
        d_ff A (.d(D_0), .clk(clk), .rst(rst), .q(out[0]));

    endmodule

Sequential Design/Design-Problem/Code/counter5.v


    module counter5 (input clk, rst, output [2:0] out);

        wire D_2, D_1, D_0;
        // D_c = D_2 = Q1 Q0 + Q2 Q0'
        assign D_2 = (out[1] & out[0]) | (out[2] & ~out[0]);

        // D_b = D_1 = Q1 Q0' + Q2' Q1' Q0
        assign D_1 = (out[1] & ~out[0]) | (~out[2] & ~out[1] & out[0]);

        // D_a = D_0 = Q0'
        assign D_0 = ~out[0];


        d_ff C (.d(D_2), .clk(clk), .rst(rst), .q(out[2]));
        d_ff B (.d(D_1), .clk(clk), .rst(rst), .q(out[1]));
        d_ff A (.d(D_0), .clk(clk), .rst(rst), .q(out[0]));

    endmodule

Sequential Design/Design-Problem/Code/stopwatch.v

module stopwatch (input clk, clr, output [3:0] min, sec0, deci, output [2:0] sec1);

//Deci
counter9 decimal (.clk(clk), .rst(clr), .out(deci));

//Second_0 (LSB)
wire clk_sec0;
assign clk_sec0 = (~deci[3] & ~deci[2] & ~deci[1] & ~deci[0]);
counter9 second_0 (.clk(clk_sec0), .rst(clr), .out(sec0));

//Second_1 (MSB)
wire clk_sec1;
assign clk_sec1 = (~sec0[3] & ~sec0[2] & ~sec0[1] & ~sec0[0]);
counter5 second_1 (.clk(clk_sec1), .rst(clr), .out(sec1));

//Minutes
wire clk_minute;
assign clk_minute = (~sec1[2] & ~sec1[1] & ~sec1[0]);
counter9 minute (.clk(clk_minute), .rst(clr), .out(min));

endmodule

Sequential Design/Design-Problem/Code/tb_stopwatch.v


    `timescale 1ms/100us
    module tb_stopwatch;
    
    //input clk, clr, output reg [3:0] min, sec0, deci, output reg [2:0] sec1
    reg clk, clr;
    wire [3:0] min, sec0, deci;
    wire [2:0] sec1;

    stopwatch dut (.clk(clk), .clr(clr), . min(min), .sec0(sec0), .deci(deci), .sec1(sec1));

    always #50 clk = ~clk;
    initial begin

        $dumpvars;
        clk = 0;
        clr = 0;

        #20;
        clr = 1;

        #300;
        clr = 0;

        #650000;
        $finish;
    end

    initial begin
        $monitor("%d : %d%d : %d",min,sec1,sec0,deci);
    end

    endmodule

Sequential Design/Design-Problem/Code/dump.vcd
$date
	Mon Jul 22 15:29:38 2024
$end
$version
	ModelSim Version 2020.1
$end
$timescale
	100us
$end

$scope module tb_stopwatch $end
$var reg 1 ! clk $end
$var reg 1 " clr $end
$var wire 1 # min [3] $end
$var wire 1 $ min [2] $end
$var wire 1 % min [1] $end
$var wire 1 & min [0] $end
$var wire 1 ' sec0 [3] $end
$var wire 1 ( sec0 [2] $end
$var wire 1 ) sec0 [1] $end
$var wire 1 * sec0 [0] $end
$var wire 1 + deci [3] $end
$var wire 1 , deci [2] $end
$var wire 1 - deci [1] $end
$var wire 1 . deci [0] $end
$var wire 1 / sec1 [2] $end
$var wire 1 0 sec1 [1] $end
$var wire 1 1 sec1 [0] $end

$scope module dut $end
$var wire 1 2 clk $end
$var wire 1 3 clr $end
$var wire 1 # min [3] $end
$var wire 1 $ min [2] $end
$var wire 1 % min [1] $end
$var wire 1 & min [0] $end
$var wire 1 ' sec0 [3] $end
$var wire 1 ( sec0 [2] $end
$var wire 1 ) sec0 [1] $end
$var wire 1 * sec0 [0] $end
$var wire 1 + deci [3] $end
$var wire 1 , deci [2] $end
$var wire 1 - deci [1] $end
$var wire 1 . deci [0] $end
$var wire 1 / sec1 [2] $end
$var wire 1 0 sec1 [1] $end
$var wire 1 1 sec1 [0] $end
$var wire 1 4 clk_sec0 $end
$var wire 1 5 clk_sec1 $end
$var wire 1 6 clk_minute $end

$scope module decimal $end
$var wire 1 2 clk $end
$var wire 1 3 rst $end
$var wire 1 + out [3] $end
$var wire 1 , out [2] $end
$var wire 1 - out [1] $end
$var wire 1 . out [0] $end
$var wire 1 7 D_3 $end
$var wire 1 8 D_2 $end
$var wire 1 9 D_1 $end
$var wire 1 : D_0 $end

$scope module D $end
$var wire 1 7 d $end
$var wire 1 2 clk $end
$var wire 1 3 rst $end
$var reg 1 ; q $end
$upscope $end

$scope module C $end
$var wire 1 8 d $end
$var wire 1 2 clk $end
$var wire 1 3 rst $end
$var reg 1 < q $end
$upscope $end

$scope module B $end
$var wire 1 9 d $end
$var wire 1 2 clk $end
$var wire 1 3 rst $end
$var reg 1 = q $end
$upscope $end

$scope module A $end
$var wire 1 : d $end
$var wire 1 2 clk $end
$var wire 1 3 rst $end
$var reg 1 > q $end
$upscope $end
$upscope $end

$scope module second_0 $end
$var wire 1 4 clk $end
$var wire 1 3 rst $end
$var wire 1 ' out [3] $end
$var wire 1 ( out [2] $end
$var wire 1 ) out [1] $end
$var wire 1 * out [0] $end
$var wire 1 ? D_3 $end
$var wire 1 @ D_2 $end
$var wire 1 A D_1 $end
$var wire 1 B D_0 $end

$scope module D $end
$var wire 1 ? d $end
$var wire 1 4 clk $end
$var wire 1 3 rst $end
$var reg 1 C q $end
$upscope $end

$scope module C $end
$var wire 1 @ d $end
$var wire 1 4 clk $end
$var wire 1 3 rst $end
$var reg 1 D q $end
$upscope $end

$scope module B $end
$var wire 1 A d $end
$var wire 1 4 clk $end
$var wire 1 3 rst $end
$var reg 1 E q $end
$upscope $end

$scope module A $end
$var wire 1 B d $end
$var wire 1 4 clk $end
$var wire 1 3 rst $end
$var reg 1 F q $end
$upscope $end
$upscope $end

$scope module second_1 $end
$var wire 1 5 clk $end
$var wire 1 3 rst $end
$var wire 1 / out [2] $end
$var wire 1 0 out [1] $end
$var wire 1 1 out [0] $end
$var wire 1 G D_2 $end
$var wire 1 H D_1 $end
$var wire 1 I D_0 $end

$scope module C $end
$var wire 1 G d $end
$var wire 1 5 clk $end
$var wire 1 3 rst $end
$var reg 1 J q $end
$upscope $end

$scope module B $end
$var wire 1 H d $end
$var wire 1 5 clk $end
$var wire 1 3 rst $end
$var reg 1 K q $end
$upscope $end

$scope module A $end
$var wire 1 I d $end
$var wire 1 5 clk $end
$var wire 1 3 rst $end
$var reg 1 L q $end
$upscope $end
$upscope $end

$scope module minute $end
$var wire 1 6 clk $end
$var wire 1 3 rst $end
$var wire 1 # out [3] $end
$var wire 1 $ out [2] $end
$var wire 1 % out [1] $end
$var wire 1 & out [0] $end
$var wire 1 M D_3 $end
$var wire 1 N D_2 $end
$var wire 1 O D_1 $end
$var wire 1 P D_0 $end

$scope module D $end
$var wire 1 M d $end
$var wire 1 6 clk $end
$var wire 1 3 rst $end
$var reg 1 Q q $end
$upscope $end

$scope module C $end
$var wire 1 N d $end
$var wire 1 6 clk $end
$var wire 1 3 rst $end
$var reg 1 R q $end
$upscope $end

$scope module B $end
$var wire 1 O d $end
$var wire 1 6 clk $end
$var wire 1 3 rst $end
$var reg 1 S q $end
$upscope $end

$scope module A $end
$var wire 1 P d $end
$var wire 1 6 clk $end
$var wire 1 3 rst $end
$var reg 1 T q $end
$upscope $end
$upscope $end
$upscope $end
$upscope $end
$enddefinitions $end
#0
$dumpvars
0!
0"
x;
x<
x=
x>
xC
xD
xE
xF
xJ
xK
xL
xQ
xR
xS
xT
x&
x%
x$
x#
x*
x)
x(
x'
x.
x-
x,
x+
x1
x0
x/
x7
x8
x9
x:
x4
x?
x@
xA
xB
x5
xG
xH
xI
x6
xM
xN
xO
xP
03
02
$end
#200
1"
13
0;
0<
0=
0>
0C
0D
0E
0F
0J
0K
0L
0Q
0R
0S
0T
0+
0,
0-
0.
0'
0(
0)
0*
0/
00
01
0#
0$
0%
0&
0O
1P
0N
0M
0H
1I
0G
0A
1B
0@
0?
09
1:
08
07
14
15
16
#500
1!
12
#1000
0!
02
#1500
1!
12
#2000
0!
02
#2500
1!
12
#3000
0!
02
#3200
0"
03
#3500
1!
12
1>
1.
19
0:
04
#4000
0!
02
#4500
1!
12
1=
0>
1-
0.
1:
#5000
0!
02
#5500
1!
12
1>
1.
18
09
0:
#6000
0!
02
#6500
1!
12
1<
0=
0>
1,
0-
0.
1:
#7000
0!
02
#7500
1!
12
1>
1.
19
0:
#8000
0!
02
#8500
1!
12
1=
0>
1-
0.
1:
#9000
0!
02
#9500
1!
12
1>
1.
17
08
09
0:
#10000
0!
02
#10500
1!
12
1;
0<
0=
0>
1+
0,
0-
0.
1:
#11000
0!
02
#11500
1!
12
1>
1.
07
0:
#12000
0!
02
#12500
1!
12
0;
0>
0+
0.
1:
14
1F
1*
1A
0B
05
#13000
0!
02
#13500
1!
12
1>
1.
19
0:
04
#14000
0!
02
#14500
1!
12
1=
0>
1-
0.
1:
#15000
0!
02
#15500
1!
12
1>
1.
18
09
0:
#16000
0!
02
#16500
1!
12
1<
0=
0>
1,
0-
0.
1:
#17000
0!
02
#17500
1!
12
1>
1.
19
0:
#18000
0!
02
#18500
1!
12
1=
0>
1-
0.
1:
#19000
0!
02
#19500
1!
12
1>
1.
17
08
09
0:
#20000
0!
02
#20500
1!
12
1;
0<
0=
0>
1+
0,
0-
0.
1:
#21000
0!
02
#21500
1!
12
1>
1.
07
0:
#22000
0!
02
#22500
1!
12
0;
0>
0+
0.
1:
14
1E
0F
1)
0*
1B
#23000
0!
02
#23500
1!
12
1>
1.
19
0:
04
#24000
0!
02
#24500
1!
12
1=
0>
1-
0.
1:
#25000
0!
02
#25500
1!
12
1>
1.
18
09
0:
#26000
0!
02
#26500
1!
12
1<
0=
0>
1,
0-
0.
1:
#27000
0!
02
#27500
1!
12
1>
1.
19
0:
#28000
0!
02
#28500
1!
12
1=
0>
1-
0.
1:
#29000
0!
02
#29500
1!
12
1>
1.
17
08
09
0:
#30000
0!
02
#30500
1!
12
1;
0<
0=
0>
1+
0,
0-
0.
1:
#31000
0!
02
#31500
1!
12
1>
1.
07
0:
#32000
0!
02
#32500
1!
12
0;
0>
0+
0.
1:
14
1F
1*
1@
0A
0B
#33000
0!
02
#33500
1!
12
1>
1.
19
0:
04
#34000
0!
02
#34500
1!
12
1=
0>
1-
0.
1:
#35000
0!
02
#35500
1!
12
1>
1.
18
09
0:
#36000
0!
02
#36500
1!
12
1<
0=
0>
1,
0-
0.
1:
#37000
0!
02
#37500
1!
12
1>
1.
19
0:
#38000
0!
02
#38500
1!
12
1=
0>
1-
0.
1:
#39000
0!
02
#39500
1!
12
1>
1.
17
08
09
0:
#40000
0!
02
#40500
1!
12
1;
0<
0=
0>
1+
0,
0-
0.
1:
#41000
0!
02
#41500
1!
12
1>
1.
07
0:
#42000
0!
02
#42500
1!
12
0;
0>
0+
0.
1:
14
1D
0E
0F
1(
0)
0*
1B
#43000
0!
02
#43500
1!
12
1>
1.
19
0:
04
#44000
0!
02
#44500
1!
12
1=
0>
1-
0.
1:
#45000
0!
02
#45500
1!
12
1>
1.
18
09
0:
#46000
0!
02
#46500
1!
12
1<
0=
0>
1,
0-
0.
1:
#47000
0!
02
#47500
1!
12
1>
1.
19
0:
#48000
0!
02
#48500
1!
12
1=
0>
1-
0.
1:
#49000
0!
02
#49500
1!
12
1>
1.
17
08
09
0:
#50000
0!
02
#50500
1!
12
1;
0<
0=
0>
1+
0,
0-
0.
1:
#51000
0!
02
#51500
1!
12
1>
1.
07
0:
#52000
0!
02
#52500
1!
12
0;
0>
0+
0.
1:
14
1F
1*
1A
0B
#53000
0!
02
#53500
1!
12
1>
1.
19
0:
04
#54000
0!
02
#54500
1!
12
1=
0>
1-
0.
1:
#55000
0!
02
#55500
1!
12
1>
1.
18
09
0:
#56000
0!
02
#56500
1!
12
1<
0=
0>
1,
0-
0.
1:
#57000
0!
02
#57500
1!
12
1>
1.
19
0:
#58000
0!
02
#58500
1!
12
1=
0>
1-
0.
1:
#59000
0!
02
#59500
1!
12
1>
1.
17
08
09
0:
#60000
0!
02
#60500
1!
12
1;
0<
0=
0>
1+
0,
0-
0.
1:
#61000
0!
02
#61500
1!
12
1>
1.
07
0:
#62000
0!
02
#62500
1!
12
0;
0>
0+
0.
1:
14
1E
0F
1)
0*
1B
#63000
0!
02
#63500
1!
12
1>
1.
19
0:
04
#64000
0!
02
#64500
1!
12
1=
0>
1-
0.
1:
#65000
0!
02
#65500
1!
12
1>
1.
18
09
0:
#66000
0!
02
#66500
1!
12
1<
0=
0>
1,
0-
0.
1:
#67000
0!
02
#67500
1!
12
1>
1.
19
0:
#68000
0!
02
#68500
1!
12
1=
0>
1-
0.
1:
#69000
0!
02
#69500
1!
12
1>
1.
17
08
09
0:
#70000
0!
02
#70500
1!
12
1;
0<
0=
0>
1+
0,
0-
0.
1:
#71000
0!
02
#71500
1!
12
1>
1.
07
0:
#72000
0!
02
#72500
1!
12
0;
0>
0+
0.
1:
14
1F
1*
1?
0@
0A
0B
#73000
0!
02
#73500
1!
12
1>
1.
19
0:
04
#74000
0!
02
#74500
1!
12
1=
0>
1-
0.
1:
#75000
0!
02
#75500
1!
12
1>
1.
18
09
0:
#76000
0!
02
#76500
1!
12
1<
0=
0>
1,
0-
0.
1:
#77000
0!
02
#77500
1!
12
1>
1.
19
0:
#78000
0!
02
#78500
1!
12
1=
0>
1-
0.
1:
#79000
0!
02
#79500
1!
12
1>
1.
17
08
09
0:
#80000
0!
02
#80500
1!
12
1;
0<
0=
0>
1+
0,
0-
0.
1:
#81000
0!
02
#81500
1!
12
1>
1.
07
0:
#82000
0!
02
#82500
1!
12
0;
0>
0+
0.
1:
14
1C
0D
0E
0F
1'
0(
0)
0*
1B
#83000
0!
02
#83500
1!
12
1>
1.
19
0:
04
#84000
0!
02
#84500
1!
12
1=
0>
1-
0.
1:
#85000
0!
02
#85500
1!
12
1>
1.
18
09
0:
#86000
0!
02
#86500
1!
12
1<
0=
0>
1,
0-
0.
1:
#87000
0!
02
#87500
1!
12
1>
1.
19
0:
#88000
0!
02
#88500
1!
12
1=
0>
1-
0.
1:
#89000
0!
02
#89500
1!
12
1>
1.
17
08
09
0:
#90000
0!
02
#90500
1!
12
1;
0<
0=
0>
1+
0,
0-
0.
1:
#91000
0!
02
#91500
1!
12
1>
1.
07
0:
#92000
0!
02
#92500
1!
12
0;
0>
0+
0.
1:
14
1F
1*
0?
0B
#93000
0!
02
#93500
1!
12
1>
1.
19
0:
04
#94000
0!
02
#94500
1!
12
1=
0>
1-
0.
1:
#95000
0!
02
#95500
1!
12
1>
1.
18
09
0:
#96000
0!
02
#96500
1!
12
1<
0=
0>
1,
0-
0.
1:
#97000
0!
02
#97500
1!
12
1>
1.
19
0:
#98000
0!
02
#98500
1!
12
1=
0>
1-
0.
1:
#99000
0!
02
#99500
1!
12
1>
1.
17
08
09
0:
#100000
0!
02
#100500
1!
12
1;
0<
0=
0>
1+
0,
0-
0.
1:
#101000
0!
02
#101500
1!
12
1>
1.
07
0:
#102000
0!
02
#102500
1!
12
0;
0>
0+
0.
1:
14
0C
0F
0'
0*
1B
15
1L
11
1H
0I
06
#103000
0!
02
#103500
1!
12
1>
1.
19
0:
04
#104000
0!
02
#104500
1!
12
1=
0>
1-
0.
1:
#105000
0!
02
#105500
1!
12
1>
1.
18
09
0:
#106000
0!
02
#106500
1!
12
1<
0=
0>
1,
0-
0.
1:
#107000
0!
02
#107500
1!
12
1>
1.
19
0:
#108000
0!
02
#108500
1!
12
1=
0>
1-
0.
1:
#109000
0!
02
#109500
1!
12
1>
1.
17
08
09
0:
#110000
0!
02
#110500
1!
12
1;
0<
0=
0>
1+
0,
0-
0.
1:
#111000
0!
02
#111500
1!
12
1>
1.
07
0:
#112000
0!
02
#112500
1!
12
0;
0>
0+
0.
1:
14
1F
1*
1A
0B
05
#113000
0!
02
#113500
1!
12
1>
1.
19
0:
04
#114000
0!
02
#114500
1!
12
1=
0>
1-
0.
1:
#115000
0!
02
#115500
1!
12
1>
1.
18
09
0:
#116000
0!
02
#116500
1!
12
1<
0=
0>
1,
0-
0.
1:
#117000
0!
02
#117500
1!
12
1>
1.
19
0:
#118000
0!
02
#118500
1!
12
1=
0>
1-
0.
1:
#119000
0!
02
#119500
1!
12
1>
1.
17
08
09
0:
#120000
0!
02
#120500
1!
12
1;
0<
0=
0>
1+
0,
0-
0.
1:
#121000
0!
02
#121500
1!
12
1>
1.
07
0:
#122000
0!
02
#122500
1!
12
0;
0>
0+
0.
1:
14
1E
0F
1)
0*
1B
#123000
0!
02
#123500
1!
12
1>
1.
19
0:
04
#124000
0!
02
#124500
1!
12
1=
0>
1-
0.
1:
#125000
0!
02
#125500
1!
12
1>
1.
18
09
0:
#126000
0!
02
#126500
1!
12
1<
0=
0>
1,
0-
0.
1:
#127000
0!
02
#127500
1!
12
1>
1.
19
0:
#128000
0!
02
#128500
1!
12
1=
0>
1-
0.
1:
#129000
0!
02
#129500
1!
12
1>
1.
17
08
09
0:
#130000
0!
02
#130500
1!
12
1;
0<
0=
0>
1+
0,
0-
0.
1:
#131000
0!
02
#131500
1!
12
1>
1.
07
0:
#132000
0!
02
#132500
1!
12
0;
0>
0+
0.
1:
14
1F
1*
1@
0A
0B
#133000
0!
02
#133500
1!
12
1>
1.
19
0:
04
#134000
0!
02
#134500
1!
12
1=
0>
1-
0.
1:
#135000
0!
02
#135500
1!
12
1>
1.
18
09
0:
#136000
0!
02
#136500
1!
12
1<
0=
0>
1,
0-
0.
1:
#137000
0!
02
#137500
1!
12
1>
1.
19
0:
#138000
0!
02
#138500
1!
12
1=
0>
1-
0.
1:
#139000
0!
02
#139500
1!
12
1>
1.
17
08
09
0:
#140000
0!
02
#140500
1!
12
1;
0<
0=
0>
1+
0,
0-
0.
1:
#141000
0!
02
#141500
1!
12
1>
1.
07
0:
#142000
0!
02
#142500
1!
12
0;
0>
0+
0.
1:
14
1D
0E
0F
1(
0)
0*
1B
#143000
0!
02
#143500
1!
12
1>
1.
19
0:
04
#144000
0!
02
#144500
1!
12
1=
0>
1-
0.
1:
#145000
0!
02
#145500
1!
12
1>
1.
18
09
0:
#146000
0!
02
#146500
1!
12
1<
0=
0>
1,
0-
0.
1:
#147000
0!
02
#147500
1!
12
1>
1.
19
0:
#148000
0!
02
#148500
1!
12
1=
0>
1-
0.
1:
#149000
0!
02
#149500
1!
12
1>
1.
17
08
09
0:
#150000
0!
02
#150500
1!
12
1;
0<
0=
0>
1+
0,
0-
0.
1:
#151000
0!
02
#151500
1!
12
1>
1.
07
0:
#152000
0!
02
#152500
1!
12
0;
0>
0+
0.
1:
14
1F
1*
1A
0B
#153000
0!
02
#153500
1!
12
1>
1.
19
0:
04
#154000
0!
02
#154500
1!
12
1=
0>
1-
0.
1:
#155000
0!
02
#155500
1!
12
1>
1.
18
09
0:
#156000
0!
02
#156500
1!
12
1<
0=
0>
1,
0-
0.
1:
#157000
0!
02
#157500
1!
12
1>
1.
19
0:
#158000
0!
02
#158500
1!
12
1=
0>
1-
0.
1:
#159000
0!
02
#159500
1!
12
1>
1.
17
08
09
0:
#160000
0!
02
#160500
1!
12
1;
0<
0=
0>
1+
0,
0-
0.
1:
#161000
0!
02
#161500
1!
12
1>
1.
07
0:
#162000
0!
02
#162500
1!
12
0;
0>
0+
0.
1:
14
1E
0F
1)
0*
1B
#163000
0!
02
#163500
1!
12
1>
1.
19
0:
04
#164000
0!
02
#164500
1!
12
1=
0>
1-
0.
1:
#165000
0!
02
#165500
1!
12
1>
1.
18
09
0:
#166000
0!
02
#166500
1!
12
1<
0=
0>
1,
0-
0.
1:
#167000
0!
02
#167500
1!
12
1>
1.
19
0:
#168000
0!
02
#168500
1!
12
1=
0>
1-
0.
1:
#169000
0!
02
#169500
1!
12
1>
1.
17
08
09
0:
#170000
0!
02
#170500
1!
12
1;
0<
0=
0>
1+
0,
0-
0.
1:
#171000
0!
02
#171500
1!
12
1>
1.
07
0:
#172000
0!
02
#172500
1!
12
0;
0>
0+
0.
1:
14
1F
1*
1?
0@
0A
0B
#173000
0!
02
#173500
1!
12
1>
1.
19
0:
04
#174000
0!
02
#174500
1!
12
1=
0>
1-
0.
1:
#175000
0!
02
#175500
1!
12
1>
1.
18
09
0:
#176000
0!
02
#176500
1!
12
1<
0=
0>
1,
0-
0.
1:
#177000
0!
02
#177500
1!
12
1>
1.
19
0:
#178000
0!
02
#178500
1!
12
1=
0>
1-
0.
1:
#179000
0!
02
#179500
1!
12
1>
1.
17
08
09
0:
#180000
0!
02
#180500
1!
12
1;
0<
0=
0>
1+
0,
0-
0.
1:
#181000
0!
02
#181500
1!
12
1>
1.
07
0:
#182000
0!
02
#182500
1!
12
0;
0>
0+
0.
1:
14
1C
0D
0E
0F
1'
0(
0)
0*
1B
#183000
0!
02
#183500
1!
12
1>
1.
19
0:
04
#184000
0!
02
#184500
1!
12
1=
0>
1-
0.
1:
#185000
0!
02
#185500
1!
12
1>
1.
18
09
0:
#186000
0!
02
#186500
1!
12
1<
0=
0>
1,
0-
0.
1:
#187000
0!
02
#187500
1!
12
1>
1.
19
0:
#188000
0!
02
#188500
1!
12
1=
0>
1-
0.
1:
#189000
0!
02
#189500
1!
12
1>
1.
17
08
09
0:
#190000
0!
02
#190500
1!
12
1;
0<
0=
0>
1+
0,
0-
0.
1:
#191000
0!
02
#191500
1!
12
1>
1.
07
0:
#192000
0!
02
#192500
1!
12
0;
0>
0+
0.
1:
14
1F
1*
0?
0B
#193000
0!
02
#193500
1!
12
1>
1.
19
0:
04
#194000
0!
02
#194500
1!
12
1=
0>
1-
0.
1:
#195000
0!
02
#195500
1!
12
1>
1.
18
09
0:
#196000
0!
02
#196500
1!
12
1<
0=
0>
1,
0-
0.
1:
#197000
0!
02
#197500
1!
12
1>
1.
19
0:
#198000
0!
02
#198500
1!
12
1=
0>
1-
0.
1:
#199000
0!
02
#199500
1!
12
1>
1.
17
08
09
0:
#200000
0!
02
#200500
1!
12
1;
0<
0=
0>
1+
0,
0-
0.
1:
#201000
0!
02
#201500
1!
12
1>
1.
07
0:
#202000
0!
02
#202500
1!
12
0;
0>
0+
0.
1:
14
0C
0F
0'
0*
1B
15
1K
0L
10
01
1I
#203000
0!
02
#203500
1!
12
1>
1.
19
0:
04
#204000
0!
02
#204500
1!
12
1=
0>
1-
0.
1:
#205000
0!
02
#205500
1!
12
1>
1.
18
09
0:
#206000
0!
02
#206500
1!
12
1<
0=
0>
1,
0-
0.
1:
#207000
0!
02
#207500
1!
12
1>
1.
19
0:
#208000
0!
02
#208500
1!
12
1=
0>
1-
0.
1:
#209000
0!
02
#209500
1!
12
1>
1.
17
08
09
0:
#210000
0!
02
#210500
1!
12
1;
0<
0=
0>
1+
0,
0-
0.
1:
#211000
0!
02
#211500
1!
12
1>
1.
07
0:
#212000
0!
02
#212500
1!
12
0;
0>
0+
0.
1:
14
1F
1*
1A
0B
05
#213000
0!
02
#213500
1!
12
1>
1.
19
0:
04
#214000
0!
02
#214500
1!
12
1=
0>
1-
0.
1:
#215000
0!
02
#215500
1!
12
1>
1.
18
09
0:
#216000
0!
02
#216500
1!
12
1<
0=
0>
1,
0-
0.
1:
#217000
0!
02
#217500
1!
12
1>
1.
19
0:
#218000
0!
02
#218500
1!
12
1=
0>
1-
0.
1:
#219000
0!
02
#219500
1!
12
1>
1.
17
08
09
0:
#220000
0!
02
#220500
1!
12
1;
0<
0=
0>
1+
0,
0-
0.
1:
#221000
0!
02
#221500
1!
12
1>
1.
07
0:
#222000
0!
02
#222500
1!
12
0;
0>
0+
0.
1:
14
1E
0F
1)
0*
1B
#223000
0!
02
#223500
1!
12
1>
1.
19
0:
04
#224000
0!
02
#224500
1!
12
1=
0>
1-
0.
1:
#225000
0!
02
#225500
1!
12
1>
1.
18
09
0:
#226000
0!
02
#226500
1!
12
1<
0=
0>
1,
0-
0.
1:
#227000
0!
02
#227500
1!
12
1>
1.
19
0:
#228000
0!
02
#228500
1!
12
1=
0>
1-
0.
1:
#229000
0!
02
#229500
1!
12
1>
1.
17
08
09
0:
#230000
0!
02
#230500
1!
12
1;
0<
0=
0>
1+
0,
0-
0.
1:
#231000
0!
02
#231500
1!
12
1>
1.
07
0:
#232000
0!
02
#232500
1!
12
0;
0>
0+
0.
1:
14
1F
1*
1@
0A
0B
#233000
0!
02
#233500
1!
12
1>
1.
19
0:
04
#234000
0!
02
#234500
1!
12
1=
0>
1-
0.
1:
#235000
0!
02
#235500
1!
12
1>
1.
18
09
0:
#236000
0!
02
#236500
1!
12
1<
0=
0>
1,
0-
0.
1:
#237000
0!
02
#237500
1!
12
1>
1.
19
0:
#238000
0!
02
#238500
1!
12
1=
0>
1-
0.
1:
#239000
0!
02
#239500
1!
12
1>
1.
17
08
09
0:
#240000
0!
02
#240500
1!
12
1;
0<
0=
0>
1+
0,
0-
0.
1:
#241000
0!
02
#241500
1!
12
1>
1.
07
0:
#242000
0!
02
#242500
1!
12
0;
0>
0+
0.
1:
14
1D
0E
0F
1(
0)
0*
1B
#243000
0!
02
#243500
1!
12
1>
1.
19
0:
04
#244000
0!
02
#244500
1!
12
1=
0>
1-
0.
1:
#245000
0!
02
#245500
1!
12
1>
1.
18
09
0:
#246000
0!
02
#246500
1!
12
1<
0=
0>
1,
0-
0.
1:
#247000
0!
02
#247500
1!
12
1>
1.
19
0:
#248000
0!
02
#248500
1!
12
1=
0>
1-
0.
1:
#249000
0!
02
#249500
1!
12
1>
1.
17
08
09
0:
#250000
0!
02
#250500
1!
12
1;
0<
0=
0>
1+
0,
0-
0.
1:
#251000
0!
02
#251500
1!
12
1>
1.
07
0:
#252000
0!
02
#252500
1!
12
0;
0>
0+
0.
1:
14
1F
1*
1A
0B
#253000
0!
02
#253500
1!
12
1>
1.
19
0:
04
#254000
0!
02
#254500
1!
12
1=
0>
1-
0.
1:
#255000
0!
02
#255500
1!
12
1>
1.
18
09
0:
#256000
0!
02
#256500
1!
12
1<
0=
0>
1,
0-
0.
1:
#257000
0!
02
#257500
1!
12
1>
1.
19
0:
#258000
0!
02
#258500
1!
12
1=
0>
1-
0.
1:
#259000
0!
02
#259500
1!
12
1>
1.
17
08
09
0:
#260000
0!
02
#260500
1!
12
1;
0<
0=
0>
1+
0,
0-
0.
1:
#261000
0!
02
#261500
1!
12
1>
1.
07
0:
#262000
0!
02
#262500
1!
12
0;
0>
0+
0.
1:
14
1E
0F
1)
0*
1B
#263000
0!
02
#263500
1!
12
1>
1.
19
0:
04
#264000
0!
02
#264500
1!
12
1=
0>
1-
0.
1:
#265000
0!
02
#265500
1!
12
1>
1.
18
09
0:
#266000
0!
02
#266500
1!
12
1<
0=
0>
1,
0-
0.
1:
#267000
0!
02
#267500
1!
12
1>
1.
19
0:
#268000
0!
02
#268500
1!
12
1=
0>
1-
0.
1:
#269000
0!
02
#269500
1!
12
1>
1.
17
08
09
0:
#270000
0!
02
#270500
1!
12
1;
0<
0=
0>
1+
0,
0-
0.
1:
#271000
0!
02
#271500
1!
12
1>
1.
07
0:
#272000
0!
02
#272500
1!
12
0;
0>
0+
0.
1:
14
1F
1*
1?
0@
0A
0B
#273000
0!
02
#273500
1!
12
1>
1.
19
0:
04
#274000
0!
02
#274500
1!
12
1=
0>
1-
0.
1:
#275000
0!
02
#275500
1!
12
1>
1.
18
09
0:
#276000
0!
02
#276500
1!
12
1<
0=
0>
1,
0-
0.
1:
#277000
0!
02
#277500
1!
12
1>
1.
19
0:
#278000
0!
02
#278500
1!
12
1=
0>
1-
0.
1:
#279000
0!
02
#279500
1!
12
1>
1.
17
08
09
0:
#280000
0!
02
#280500
1!
12
1;
0<
0=
0>
1+
0,
0-
0.
1:
#281000
0!
02
#281500
1!
12
1>
1.
07
0:
#282000
0!
02
#282500
1!
12
0;
0>
0+
0.
1:
14
1C
0D
0E
0F
1'
0(
0)
0*
1B
#283000
0!
02
#283500
1!
12
1>
1.
19
0:
04
#284000
0!
02
#284500
1!
12
1=
0>
1-
0.
1:
#285000
0!
02
#285500
1!
12
1>
1.
18
09
0:
#286000
0!
02
#286500
1!
12
1<
0=
0>
1,
0-
0.
1:
#287000
0!
02
#287500
1!
12
1>
1.
19
0:
#288000
0!
02
#288500
1!
12
1=
0>
1-
0.
1:
#289000
0!
02
#289500
1!
12
1>
1.
17
08
09
0:
#290000
0!
02
#290500
1!
12
1;
0<
0=
0>
1+
0,
0-
0.
1:
#291000
0!
02
#291500
1!
12
1>
1.
07
0:
#292000
0!
02
#292500
1!
12
0;
0>
0+
0.
1:
14
1F
1*
0?
0B
#293000
0!
02
#293500
1!
12
1>
1.
19
0:
04
#294000
0!
02
#294500
1!
12
1=
0>
1-
0.
1:
#295000
0!
02
#295500
1!
12
1>
1.
18
09
0:
#296000
0!
02
#296500
1!
12
1<
0=
0>
1,
0-
0.
1:
#297000
0!
02
#297500
1!
12
1>
1.
19
0:
#298000
0!
02
#298500
1!
12
1=
0>
1-
0.
1:
#299000
0!
02
#299500
1!
12
1>
1.
17
08
09
0:
#300000
0!
02
#300500
1!
12
1;
0<
0=
0>
1+
0,
0-
0.
1:
#301000
0!
02
#301500
1!
12
1>
1.
07
0:
