Sequential Design/Assignment-1/Code/Question2/FSM.v
    module FSM (input clk, rst, X, Y, output reg state);

    localparam A = 1'b0;
    localparam B = 1'b1;
    
    reg next_state;
    
    //state-transition logic
    always @(posedge clk or posedge rst)
    begin
        if (rst)
        state <= A;
        else
        state <= next_state;
    end

    //Next State Logic
    always @(*) begin
        case (state)
        
        A : begin if (X && ~Y) begin 
            next_state = B;
        end
        else next_state = A; 
        end

        B : begin if (X && ~Y) begin 
            next_state = B;
        end
        else next_state = A; 
        end

        default : next_state = A;
        endcase
    end
    endmodule

Sequential Design/Assignment-1/Code/Question2/tb_FSM.v


module tb_FSM;

    // Inputs
    reg clk;
    reg rst;
    reg X;
    reg Y;

    wire state;

    FSM dut (
        .clk(clk),
        .rst(rst),
        .X(X),
        .Y(Y),
        .state(state));

    // Generate the clock and reset
    always #5 clk = ~clk;
    initial begin
        $dumpvars;

        clk = 0;
        rst = 0;

        repeat (4) @(posedge clk)
        rst = 1;
        
        @(posedge clk)
        rst = 0;

        repeat(2) @(posedge clk)
        X = 0;
        Y = 0;
        if (state != 0)
            $display("Error: Initial state hasn't been reset");

        repeat(5) @(posedge clk)
        X = 0;
        Y = 1;
        
        if (state != 0) begin
            $display("Error");
            $finish;
        end

        repeat(5) @(posedge clk)
        X = 1;
        Y = 1;
        
        if (state != 0) begin
            $display("Error");
            $finish;
        end

        repeat (2) @(posedge clk)
        X = 0;
        Y = 0;

        repeat(5) @(posedge clk)
        X = 1;
        Y = 0;
        
        if (state != 1) begin
            $display("Error: The FSM failed to transition from A to B");
            $finish;
        end

        repeat(5) @(posedge clk)

        //No change in input, should stay in state B        
        if (state != 1) begin
            $display("Error: The FSM failed to stay in B");
            $finish;
        end

        repeat(5) @(posedge clk)
        X = 0;
        Y = 1;
        
        if (state != 0) begin
            $display("Error: The FSM failed to transition from B to A");
            $finish;
        end
        
        $display("All Test Cases Passed Successfully");
        $finish;
    end

endmodule

Sequential Design/Assignment-1/Code/Question2/dump.vcd
$date
	Fri Jul 26 15:19:54 2024
$end
$version
	ModelSim Version 2020.1
$end
$timescale
	1ps
$end

$scope module tb_FSM $end
$var reg 1 ! clk $end
$var reg 1 " rst $end
$var reg 1 # X $end
$var reg 1 $ Y $end
$var wire 1 % state $end

$scope module dut $end
$var parameter 1 & A $end
$var parameter 1 ' B $end
$var wire 1 ( clk $end
$var wire 1 ) rst $end
$var wire 1 * X $end
$var wire 1 + Y $end
$var reg 1 , state $end
$var reg 1 - next_state $end
$upscope $end
$upscope $end
$enddefinitions $end
#0
$dumpvars
0!
0"
x#
x$
x,
x-
b0 &
b1 '
x%
x+
x*
0)
0(
$end
#5
1!
1(
1"
1)
0,
0%
0-
#10
0!
0(
#15
1!
1(
#20
0!
0(
#25
1!
1(
#30
0!
0(
#35
1!
1(
#40
0!
0(
#45
1!
1(
0"
0)
#50
0!
0(
#55
1!
1(
0#
0*
#60
0!
0(
#65
1!
1(
0$
0+
#70
0!
0(
#75
1!
1(
#80
0!
0(
#85
1!
1(
#90
0!
0(
#95
1!
1(
#100
0!
0(
#105
1!
1(
#110
0!
0(
#115
1!
1(
1$
1+
#120
0!
0(
#125
1!
1(
1#
1*
#130
0!
0(
#135
1!
1(
#140
0!
0(
#145
1!
1(
#150
0!
0(
#155
1!
1(
#160
0!
0(
#165
1!
1(
#170
0!
0(
#175
1!
1(
0#
0*
#180
0!
0(
#185
1!
1(
0$
0+
#190
0!
0(
#195
1!
1(
1#
1*
1-
#200
0!
0(
#205
1!
1(
1,
1%
#210
0!
0(
#215
1!
1(
#220
0!
0(
#225
1!
1(
#230
0!
0(
#235
1!
1(
#240
0!
0(
#245
1!
1(
#250
0!
0(
#255
1!
1(
#260
0!
0(
#265
1!
1(
#270
0!
0(
#275
1!
1(
#280
0!
0(
#285
1!
1(
#290
0!
0(
#295
1!
1(
0#
0*
0-
#300
0!
0(
#305
1!
1(
0,
0%
#310
0!
0(
#315
1!
1(
#320
0!
0(
#325
1!
1(
#330
0!
0(
#335
1!
1(
1$
