Combinational Design/Design Problem/Code/shifter_cicuit.v
//Author: Noman Rafiq
//Date: July 11, 2024

module shifter_circuit (input [7:0] data_in, input [2:0] shift_amount, input shift_direction, output reg [7:0] result);


//Function Definition
function [7:0] shifted_value (input [7:0] data_in, input [2:0] shift_amount, input shift_direction);
begin
if(shift_direction)
shifted_value = (data_in << shift_amount);
else
shifted_value = (data_in >> shift_amount);
end
endfunction

always @(*)
    begin
        result = shifted_value(data_in, shift_amount, shift_direction);
    end

endmodule

Combinational Design/Design Problem/Code/tb_shifter_circuit.v

module tb_shifter_circuit;

  reg [7:0] data_in;
  reg [2:0] shift_amount;
  reg shift_direction;
  wire [7:0] result;

integer results_file;
  // Instantiating the shifter_circuit module
  shifter_circuit dut (
    .data_in(data_in),
    .shift_amount(shift_amount),
    .shift_direction(shift_direction),
    .result(result)
  );

  
  initial begin
    $dumpfile("wavetrace.vcd"); 
    $dumpvars(0, tb_shifter_circuit);

    results_file = $fopen("results.txt", "w");

    // Generate 10 random test cases
    repeat (10) begin
      data_in = $random;
      shift_amount = $random;
      shift_direction = $random;

      #10; 

      // Self-Checks
      if (result == shifted_value(data_in, shift_amount, shift_direction))
        $display("Test passed for data_in=%d, shift_amount=%d, shift_direction=%b", data_in, shift_amount, shift_direction);
      else
        $display("Test failed for data_in=%d, shift_amount=%d, shift_direction=%b", data_in, shift_amount, shift_direction);

      $fwrite(results_file, "data_in=%d, shift_amount=%d, shift_direction=%b, result=%d\n", data_in, shift_amount, shift_direction, result);
    end

    $fclose(results_file);
        $finish;
  end

function [7:0] shifted_value (input [7:0] data_in, input [2:0] shift_amount, input shift_direction);
begin
if(shift_direction)
shifted_value = (data_in << shift_amount);
else
shifted_value = (data_in >> shift_amount);
end
endfunction

endmodule

Combinational Design/Design Problem/Code/wavetrace.vcd
$date
	Thu Jul 11 11:34:51 2024
$end
$version
	ModelSim Version 2020.1
$end
$timescale
	1ps
$end

$scope module tb_shifter_circuit $end
$var reg 8 ! data_in [7:0] $end
$var reg 3 " shift_amount [2:0] $end
$var reg 1 # shift_direction $end
$var wire 1 $ result [7] $end
$var wire 1 % result [6] $end
$var wire 1 & result [5] $end
$var wire 1 ' result [4] $end
$var wire 1 ( result [3] $end
$var wire 1 ) result [2] $end
$var wire 1 * result [1] $end
$var wire 1 + result [0] $end
$var integer 32 , results_file $end

$scope function shifted_value $end
$var reg 8 - shifted_value [7:0] $end
$var reg 8 . data_in [7:0] $end
$var reg 3 / shift_amount [2:0] $end
$var reg 1 0 shift_direction $end
$upscope $end

$scope module dut $end
$var wire 1 1 data_in [7] $end
$var wire 1 2 data_in [6] $end
$var wire 1 3 data_in [5] $end
$var wire 1 4 data_in [4] $end
$var wire 1 5 data_in [3] $end
$var wire 1 6 data_in [2] $end
$var wire 1 7 data_in [1] $end
$var wire 1 8 data_in [0] $end
$var wire 1 9 shift_amount [2] $end
$var wire 1 : shift_amount [1] $end
$var wire 1 ; shift_amount [0] $end
$var wire 1 < shift_direction $end
$var reg 8 = result [7:0] $end

$scope function shifted_value $end
$var reg 8 > shifted_value [7:0] $end
$var reg 8 ? data_in [7:0] $end
$var reg 3 @ shift_amount [2:0] $end
$var reg 1 A shift_direction $end
$upscope $end
$upscope $end
$upscope $end
$enddefinitions $end
#0
$dumpvars
b100100 !
b1 "
1#
b1001000 =
b1001000 >
b100100 ?
b1 @
1A
bx -
bx .
bx /
x0
b10000000000000000000000000000011 ,
0+
0*
0)
1(
0'
0&
1%
0$
1<
1;
0:
09
08
07
16
05
04
13
02
01
$end
#10
b100100 .
b1 /
10
b1001000 -
b1100011 !
b101 "
19
18
17
06
12
b1100011 ?
b101 @
b1100000 >
b1100000 =
0(
1&
#20
b1100011 .
b101 /
b1100000 -
b1100101 !
b10 "
0;
1:
09
07
16
b1100101 ?
b10 @
b10010100 >
b10010100 =
1)
1'
0&
0%
1$
#30
b1100101 .
b10 /
b10010100 -
b1101 !
b110 "
19
15
03
02
b1101 ?
b110 @
b1000000 >
b1000000 =
0)
0'
1%
0$
#40
b1101 .
b110 /
b1000000 -
b11101101 !
b100 "
0:
13
12
11
b11101101 ?
b100 @
b11010000 >
b11010000 =
1'
1$
#50
b11101101 .
b100 /
b11010000 -
b11000110 !
b101 "
0#
1;
08
17
05
03
0<
b11000110 ?
b101 @
0A
b110 >
b110 =
1*
1)
0'
0%
0$
#60
b11000110 .
b101 /
00
b110 -
b11100101 !
b111 "
1:
18
07
13
b11100101 ?
b111 @
b1 >
b1 =
1+
0*
0)
#70
b11100101 .
b111 /
b1 -
b10001111 !
b10 "
0;
09
17
15
03
02
b10001111 ?
b10 @
b100011 >
b100011 =
1*
1&
#80
b10001111 .
b10 /
b100011 -
b11101000 !
b101 "
1;
0:
19
08
07
06
13
12
b11101000 ?
b101 @
b111 >
b111 =
1)
0&
#90
b11101000 .
b101 /
b111 -
b10111101 !
1#
18
16
14
02
1<
b10111101 ?
1A
b10100000 >
b10100000 =
0+
0*
0)
1&
1$
#100
b10111101 .
10
b10100000 -
