Sequential Design/Assignment-1/Code/Question6/shift_register.v


    module shift_register (input clk, rst, load, shift, input [3:0] data_in, output reg [3:0] A);
    
    always @(posedge clk or posedge rst)
    if (rst)
        A <= 4'd0;
    else 
    begin
        case ({shift, load})
        2'b00 : A <= A;
        2'b01 : A <= data_in;
        default : A <= A << 1;
        endcase
    end
    endmodule

Sequential Design/Assignment-1/Code/Question6/tb_shift_register.v

    //Author: Noman Rafiq
//Dated: July 15, 2024

module tb_shift_register;

    // Inputs
    reg [3:0] data_in;
    reg shift;
    reg load;
    reg clk;
    reg rst;

    // Output
    wire [3:0] A;

    // Instantiate the shift register
    shift_register uut (
        .data_in(data_in),
        .shift(shift),
        .load(load),
        .clk(clk),
        .rst(rst),
        .A(A)
    );

    // Clock generation
    always #5 clk = ~clk;

    // Initial values
    initial begin

        $dumpvars;

        clk = 0;
        rst = 1;
        data_in = 4'b0000;
        shift = 0;
        load = 0;

        // Reset
        #10 rst = 0;

        // Test case 1: Load parallel data
        #20 data_in = 4'b1010;
        #10 load = 1;
        #10 load = 0;

        // Test case 2: Shift register
        #20 shift = 1;
        #20 shift = 0;

        // Test case 3: No change
        #20;

        // Test case 4: Load new data and then shift
        #20 data_in = 4'b1100;
        #10 load = 1;
        #10 load = 0;
        #20 shift = 1;
        #20 shift = 0;

        // Test case 5: Shift without loading new data
        #40 shift = 1;
        #20 shift = 0;

        // Test case 6: Shifting while shift and load are set to 1
        #20 data_in = 4'b1111;
        #10 load = 1;
        #10 load = 0;
        
        #40 shift = 1;
            load = 1;
        #20 shift = 1;
            load = 0;
        #20 shift = 0;
            load = 0;
        // End simulation
        #10 $finish;
    end

endmodule

Sequential Design/Assignment-1/Code/Question6/dump.vcd
$date
	Mon Jul 15 16:13:37 2024
$end
$version
	ModelSim Version 2020.1
$end
$timescale
	1ps
$end

$scope module tb_shift_register $end
$var reg 4 ! data_in [3:0] $end
$var reg 1 " shift $end
$var reg 1 # load $end
$var reg 1 $ clk $end
$var reg 1 % rst $end
$var wire 1 & A [3] $end
$var wire 1 ' A [2] $end
$var wire 1 ( A [1] $end
$var wire 1 ) A [0] $end

$scope module uut $end
$var wire 1 * clk $end
$var wire 1 + rst $end
$var wire 1 , load $end
$var wire 1 - shift $end
$var wire 1 . data_in [3] $end
$var wire 1 / data_in [2] $end
$var wire 1 0 data_in [1] $end
$var wire 1 1 data_in [0] $end
$var reg 4 2 A [3:0] $end
$upscope $end
$upscope $end
$enddefinitions $end
#0
$dumpvars
b0 !
0"
0#
0$
1%
b0 2
0)
0(
0'
0&
1+
0*
0,
0-
01
00
0/
0.
$end
#5
1$
1*
#10
0%
0$
0+
0*
#15
1$
1*
#20
0$
0*
#25
1$
1*
#30
b1010 !
0$
10
1.
0*
#35
1$
1*
#40
1#
0$
1,
0*
#45
1$
1*
b1010 2
1(
1&
#50
0#
0$
0,
0*
#55
1$
1*
#60
0$
0*
#65
1$
1*
#70
1"
0$
1-
0*
#75
1$
1*
b100 2
0(
1'
0&
#80
0$
0*
#85
1$
1*
b1000 2
0'
1&
#90
0"
0$
0-
0*
#95
1$
1*
#100
0$
0*
#105
1$
1*
#110
0$
0*
#115
1$
1*
#120
0$
0*
#125
1$
1*
#130
b1100 !
0$
00
1/
0*
#135
1$
1*
#140
1#
0$
1,
0*
#145
1$
1*
b1100 2
1'
#150
0#
0$
0,
0*
#155
1$
1*
#160
0$
0*
#165
1$
1*
#170
1"
0$
1-
0*
#175
1$
1*
b1000 2
0'
#180
0$
0*
#185
1$
1*
b0 2
0&
#190
0"
0$
0-
0*
#195
1$
1*
#200
0$
0*
#205
1$
1*
#210
0$
0*
#215
1$
1*
#220
0$
0*
#225
1$
1*
#230
1"
0$
1-
0*
#235
1$
1*
#240
0$
0*
#245
1$
1*
#250
0"
0$
0-
0*
#255
1$
1*
#260
0$
0*
#265
1$
1*
#270
b1111 !
0$
11
10
0*
#275
1$
1*
#280
1#
0$
1,
0*
#285
1$
1*
b1111 2
1)
1(
1'
1&
#290
0#
0$
0,
0*
#295
1$
1*
#300
0$
0*
#305
1$
1*
#310
0$
0*
#315
1$
1*
#320
0$
0*
#325
1$
1*
#330
1"
1#
0$
1-
1,
0*
#335
1$
1*
b1110 2
0)
#340
0$
0*
#345
1$
1*
b1100 2
0(
#350
0#
0$
0,
0*
#355
1$
1*
b1000 2
0'
#360
0$
0*
#365
1$
1*
b0 2
0&
#370
0"
0$
0-
0*
